Workbook

Sheet Summary
A1: Dashboard
A2: Founder case vs market case — every tile is a formula; change the blue cells on Inputs and this page updates.
A4: =IF(ISNUMBER(Founder!B11),TEXT(Founder!B11,"0.0")&"×","n/a")&" | "&IF(ISNUMBER(Market!B11),TEXT(Market!B11,"0.0")&"×","n/a") -> 80.8× | 19.4× | C4: =Founder!B12&" | "&Market!B12 -> 2 | 2 | E4: =Founder!B53&" | "&Market!B53 -> 22 | none | G4: =TEXT(Founder!B54,"#,##0")&" | "&TEXT(Market!B54,"#,##0") -> 60,310 | 358,475 | I4: =TEXT(Founder!F51,"#,##0")&" | "&TEXT(Market!F51,"#,##0") -> 11,037 | 3,922 | K4: =IF(Market!B4*Market!B10>0,3*Market!B7/(Market!B10/Market!B3),0) -> 20.742752
A5: LTV / CAC (cash) — founder | market | C5: Payback, months — founder | market | E5: Break-even month — founder | market | G5: Peak capital need — founder | market | I5: Revenue month 36 — founder | market | K5: Revenue per customer needed for LTV/CAC = 3 (market)
A7: Metric | B7: Founder | C7: Market | D7: Pessimistic | E7: Optimistic
A8: Blended CAC | B8: =Founder!B7 -> 100 | C8: =Market!B7 -> 100 | D8: =Pessimistic!B7 -> 100 | E8: =Optimistic!B7 -> 100
A9: LTV (lifetime gross-margin contribution, 60-mo cap) | B9: =Founder!B10 -> 8078.929 | C9: =Market!B10 -> 1938.0264 | D9: =Pessimistic!B10 -> 907.97634 | E9: =Optimistic!B10 -> 4102.6102
A10: LTV / CAC (cash) | B10: =Founder!B11 -> 80.78929 | C10: =Market!B11 -> 19.380264 | D10: =Pessimistic!B11 -> 9.0797634 | E10: =Optimistic!B11 -> 41.026102
A11: Payback (months, cumulative) | B11: =Founder!B12 -> 2 | C11: =Market!B12 -> 2 | D11: =Pessimistic!B12 -> 3 | E11: =Optimistic!B12 -> 2
A12: Gross margin | B12: =Founder!B4 -> 0.919 | C12: =Market!B4 -> 0.8 | D12: =Pessimistic!B4 -> 0.7 | E12: =Optimistic!B4 -> 0.9
A13: Break-even month | B13: =Founder!B53 -> 22 | C13: =Market!B53 -> none | D13: =Pessimistic!B53 -> none | E13: =Optimistic!B53 -> 36
A14: Peak capital need | B14: =Founder!B54 -> 60309.965 | C14: =Market!B54 -> 358474.57 | D14: =Pessimistic!B54 -> 561431.29 | E14: =Optimistic!B54 -> 108355.32
A15: Revenue month 12 | B15: =Founder!F27 -> 3884.6871 | C15: =Market!F27 -> 2321.0753 | D15: =Pessimistic!F27 -> 1187.2931 | E15: =Optimistic!F27 -> 4067.0778
A16: Revenue month 24 | B16: =Founder!F39 -> 7460.6793 | C16: =Market!F39 -> 3360.6507 | D16: =Pessimistic!F39 -> 1414.6495 | E16: =Optimistic!F39 -> 6836.977
A17: Revenue month 36 | B17: =Founder!F51 -> 11036.679 | C17: =Market!F51 -> 3922.3993 | D17: =Pessimistic!F51 -> 1509.8214 | E17: =Optimistic!F51 -> 8758.858
A18: Customers month 36 | B18: =Founder!D51 -> 74.071673 | C18: =Market!D51 -> 29.165665 | D18: =Pessimistic!D51 -> 15.028456 | E18: =Optimistic!D51 -> 52.064742
A19: Reference customers (3y) | B19: =Founder!B55 -> 75.36 | C19: =Market!B55 -> 75.36 | D19: =Pessimistic!B55 -> 37.68 | E19: =Optimistic!B55 -> 113.04
A20: Ratio to reference | B20: =Founder!B57 -> 0.98290437 | C20: =Market!B57 -> 0.38701785 | D20: =Pessimistic!B57 -> 0.39884437 | E20: =Optimistic!B57 -> 0.46058689
A21: Position vs comparables | B21: =Founder!B58 -> within_range | C21: =Market!B58 -> within_range | D21: =Pessimistic!B58 -> within_range | E21: =Optimistic!B58 -> within_range
A24: Month | B24: Rev Founder | C24: Rev Market | D24: Rev Pessimistic | E24: Rev Optimistic | F24: Cash Founder | G24: Cash Market | H24: Cash Pessimistic | I24: Cash Optimistic | J24: Units Founder | K24: Units Market | L24: Units Pessimistic | M24: Units Optimistic
A25: 1 | B25: =Founder!F16 -> 894 | C25: =Market!F16 -> 849.3 | D25: =Pessimistic!F16 -> 831.42 | E25: =Optimistic!F16 -> 867.18 | F25: =Founder!K16 -> -5278.414 | G25: =Market!K16 -> -11380.56 | H25: =Pessimistic!K16 -> -15842.006 | I25: =Optimistic!K16 -> -6915.538 | J25: =Founder!D16 -> 6 | K25: =Market!D16 -> 5.7 | L25: =Pessimistic!D16 -> 5.58 | M25: =Optimistic!D16 -> 5.82
A26: 2 | B26: =Founder!F17 -> 1043 | C26: =Market!F17 -> 921.405 | D26: =Pessimistic!F17 -> 828.4626 | E26: =Optimistic!F17 -> 1037.8806 | F26: =Founder!K17 -> -10466.109 | G26: =Market!K17 -> -22745.027 | H26: =Pessimistic!K17 -> -31713.809 | I26: =Optimistic!K17 -> -13732.9 | J26: =Founder!D17 -> 7 | K26: =Market!D17 -> 6.27 | L26: =Pessimistic!D17 -> 5.7474 | M26: =Optimistic!D17 -> 6.8094
A27: 3 | B27: =Founder!F18 -> 1260.8555 | C27: =Market!F18 -> 1042.8495 | D27: =Pessimistic!F18 -> 851.24049 | E27: =Optimistic!F18 -> 1294.366 | F27: =Founder!K18 -> -15483.542 | G27: =Market!K18 -> -34039.29 | H27: =Pessimistic!K18 -> -47587.637 | I27: =Optimistic!K18 -> -20355.361 | J27: =Founder!D18 -> 8.4621172 | K27: =Market!D18 -> 7.2066102 | L27: =Pessimistic!D18 -> 6.1609434 | M27: =Optimistic!D18 -> 8.3070224
A28: 4 | B28: =Founder!F19 -> 1523.333 | C28: =Market!F19 -> 1192.5329 | D28: =Pessimistic!F19 -> 888.96764 | E28: =Optimistic!F19 -> 1602.0688 | F28: =Founder!K19 -> -20274.114 | G28: =Market!K19 -> -45226.727 | H28: =Pessimistic!K19 -> -63443.668 | I28: =Optimistic!K19 -> -26718.117 | J28: =Founder!D19 -> 10.223711 | K28: =Market!D19 -> 8.3524427 | L28: =Pessimistic!D19 -> 6.7126469 | M28: =Optimistic!D19 -> 10.108307
A29: 5 | B29: =Founder!F20 -> 1807.2001 | C29: =Market!F20 -> 1351.1791 | D29: =Pessimistic!F20 -> 931.98411 | E29: =Optimistic!F20 -> 1928.7799 | F29: =Founder!K20 -> -24809.7 | G29: =Market!K20 -> -56292.547 | H29: =Pessimistic!K20 -> -79273.121 | I29: =Optimistic!K20 -> -32793.899 | J29: =Founder!D20 -> 12.12886 | K29: =Market!D20 -> 9.5637223 | L29: =Pessimistic!D20 -> 7.3058343 | M29: =Optimistic!D20 -> 12.022651
A30: 6 | B30: =Founder!F21 -> 2099.8402 | C30: =Market!F21 -> 1508.6388 | D30: =Pessimistic!F21 -> 975.24203 | E30: =Optimistic!F21 -> 2257.2721 | F30: =Founder!K21 -> -29078.608 | G30: =Market!K21 -> -67234.431 | H30: =Pessimistic!K21 -> -95073.648 | I30: =Optimistic!K21 -> -38576.747 | J30: =Founder!D21 -> 14.092887 | K30: =Market!D21 -> 10.76478 | L30: =Pessimistic!D21 -> 7.8903533 | M30: =Optimistic!D21 -> 13.948099
A31: 7 | B31: =Founder!F22 -> 2395.8457 | C31: =Market!F22 -> 1660.8132 | D31: =Pessimistic!F22 -> 1016.7196 | E31: =Optimistic!F22 -> 2580.3528 | F31: =Founder!K22 -> -33076.331 | G31: =Market!K22 -> -78055.335 | H31: =Pessimistic!K22 -> -110845.65 | I31: =Optimistic!K22 -> -44069.837 | J31: =Founder!D22 -> 16.079501 | K31: =Market!D22 -> 11.925096 | L31: =Pessimistic!D22 -> 8.4465594 | M31: =Optimistic!D22 -> 15.842075
A32: 8 | B32: =Founder!F23 -> 2693.1089 | C32: =Market!F23 -> 1806.346 | D32: =Pessimistic!F23 -> 1055.7601 | E32: =Optimistic!F23 -> 2895.4014 | F32: =Founder!K23 -> -36801.182 | G32: =Market!K23 -> -88760.095 | H32: =Pessimistic!K23 -> -126590.51 | I32: =Optimistic!K23 -> -49279.757 | J32: =Founder!D23 -> 18.074556 | K32: =Market!D23 -> 13.034613 | L32: =Pessimistic!D23 -> 8.9685408 | M32: =Optimistic!D23 -> 17.689057
A33: 9 | B33: =Founder!F24 -> 2990.8374 | C33: =Market!F24 -> 1944.9599 | D33: =Pessimistic!F24 -> 1092.2402 | E33: =Optimistic!F24 -> 3201.6129 | F33: =Founder!K24 -> -40252.535 | G33: =Market!K24 -> -99354.066 | H33: =Pessimistic!K24 -> -142309.9 | I33: =Optimistic!K24 -> -54214.225 | J33: =Founder!D24 -> 20.072734 | K33: =Market!D24 -> 14.091324 | L33: =Pessimistic!D24 -> 9.4557262 | M33: =Optimistic!D24 -> 19.484264
A34: 10 | B34: =Founder!F25 -> 3288.7374 | C34: =Market!F25 -> 2076.7751 | D34: =Pessimistic!F25 -> 1126.2303 | E34: =Optimistic!F25 -> 3498.8646 | F34: =Founder!K25 -> -43430.161 | G34: =Market!K25 -> -109842.62 | H34: =Pessimistic!K25 -> -158005.52 | I34: =Optimistic!K25 -> -58881.217 | J34: =Founder!D25 -> 22.072063 | K34: =Market!D25 -> 15.096185 | L34: =Pessimistic!D25 -> 9.9094511 | M34: =Optimistic!D25 -> 21.226956
A35: 11 | B35: =Founder!F26 -> 3586.7007 | C35: =Market!F26 -> 2202.0481 | D35: =Pessimistic!F26 -> 1157.8646 | E35: =Optimistic!F26 -> 3787.2821 | F35: =Founder!K26 -> -46333.974 | G35: =Market!K26 -> -120230.98 | H35: =Pessimistic!K26 -> -173679.01 | I35: =Optimistic!K26 -> -63288.652 | J35: =Founder!D26 -> 24.071817 | K35: =Market!D26 -> 16.051165 | L35: =Pessimistic!D26 -> 10.331652 | M35: =Optimistic!D26 -> 22.91786
A36: 12 | B36: =Founder!F27 -> 3884.6871 | C36: =Market!F27 -> 2321.0753 | D36: =Pessimistic!F27 -> 1187.2931 | E36: =Optimistic!F27 -> 4067.0778 | F36: =Founder!K27 -> -48963.943 | G36: =Market!K27 -> -130524.11 | H36: =Pessimistic!K27 -> -189331.9 | I36: =Optimistic!K27 -> -67444.278 | J36: =Founder!D27 -> 26.071726 | K36: =Market!D27 -> 16.958529 | L36: =Pessimistic!D27 -> 10.724386 | M36: =Optimistic!D27 -> 24.558218
... A60: 36 | B60: =Founder!F51 -> 11036.679 | C60: =Market!F51 -> 3922.3993 | D60: =Pessimistic!F51 -> 1509.8214 | E60: =Optimistic!F51 -> 8758.858 | F60: =Founder!K51 -> -29924.851 | G60: =Market!K51 -> -358474.57 | H60: =Pessimistic!K51 -> -561431.29 | I60: =Optimistic!K51 -> -108288.35 | J60: =Founder!D51 -> 74.071673 | K60: =Market!D51 -> 29.165665 | L60: =Pessimistic!D51 -> 15.028456 | M60: =Optimistic!D51 -> 52.064742

Sheet Growth
A1: Growth funnel (documentation of where the capacity number came from)
A3: Motion: founder_led · ramp 50% at month 1 · lag 0 mo
A5: Funnel step | B5: Value | C5: Source
A6: LinkedIn outreach + dental-association events → demos per month | B6: 8 | C6: founder_stated ('about 8 demos a month'); capacity benchmark capacity.founder_led 8–15 meetings/week (unverified) is far above this
A7: demo → paying clinic (%) | B7: 25 | C7: founder_stated ('roughly one in four'); market conv.demo.close.smb 15–30 % · secondary
A8: new clinics per month at full capacity | B8: 2 | C8: computed: 8 × 25 %; market 1.2–2.4 = 8 × 15–30 %
A10: The resulting capacity is the blue 'New customers per month at full capacity' input. Edit it there.

Sheet Inputs
A1: Assumptions — founder vs market
A2: Revenue unit: subscription. Blue cells are inputs. Founder = the founder's number; Market = midpoint of the benchmark range (low/high feed the pessimistic and optimistic cases).
A4: Assumption | B4: Founder | C4: Market (mid) | D4: Market low | E4: Market high | F4: Founder status | G4: Market source
A5: Price | B5: 149 | C5: =AVERAGE(D5,E5) -> 134 | D5: 99 | E5: 169 | F5: founder_stated | G5: Dr. Flex Booking-Flat €99 (1 calendar) – €169 (3 calendars) per practice per month, incl. digitale Nachrückerliste + reminders, published prices https://dr-flex.de/aerzte/preis · primary · 2026
A6: Gross margin | B6: 0.919 | C6: =AVERAGE(D6,E6) -> 0.8 | D6: 0.7 | E6: 0.9 | F6: founder_stated | G6: margin.saas · survey · 2024 (stale; no fresher primary found in this run)
A7: Monthly churn | B7: 0 | C7: =AVERAGE(D7,E7) -> 0.05 | D7: 0.03 | E7: 0.07 | F7: founder_stated | G7: churn.saas.smb.2026 · secondary · 2026-01; ChartMogul <$300k ARR median 6.5 %/month
A8: Expansion | B8: 0 | C8: =AVERAGE(D8,E8) -> 0 | D8: 0 | E8: 0 | F8: founder_stated | G8: default 0
A9: New customers per month | B9: 2 | C9: =AVERAGE(D9,E9) -> 1.8 | D9: 1.2 | E9: 2.4 | F9: founder_stated | G9: derived: 8 demos/month (founder_stated) × conv.demo.close.smb 15–30 % demo→close · secondary
A10: Cost per fte per month | B10: 3000 | C10: =AVERAGE(D10,E10) -> 5985 | D10: 3788 | E10: 8182 | F10: founder_stated | G10: derived: low = Kruze Consulting US pre-seed founder salary ~$50k/yr ÷ 12 ÷ 1.10 (secondary, 2025); high = fte.cost.region mid $9 000 ÷ 1.10 (secondary, unverified)
A11: Cost to acquire | B11: 100 | C11: =AVERAGE(D11,E11) -> 100 | D11: =B11 -> 100 | E11: =B11 -> 100 | F11: founder_stated · unverified
A13: Scalars (same in every case)
A14: Team size (FTE) | B14: 2
A15: Fixed monthly overhead (content, licences, infra floor) | B15: 0
A16: Upfront investment before first revenue | B16: 0
A17: Free months per new customer (long trial) | B17: 1
A18: Founder time per new customer, value of unpaid hours (not cash; ratios only) | B18: 281
A19: Starting paying customers (post-revenue only, measured) | B19: 6
A20: Starting monthly revenue (post-revenue only, measured) | B20: 894
A21: Ramp: month at 50% capacity | B21: 1
A22: Ramp: steepness k (0 = no ramp) | B22: 1
A23: Sales-cycle lag (months) | B23: 0
A24: Comparable benchmark: segment size (customers) | B24: 3768
A25: Comparable penetration after ~3 years (founder/market = mid; low/high edges) | B25: =AVERAGE(D25,E25) -> 0.02 | C25: =AVERAGE(D25,E25) -> 0.02 | D25: 0.01 | E25: 0.03
A27: Acquisition channels — the founder's CAC is the volume-weighted average of this table
A28: Channel | B28: Customers / month | C28: Channel CAC | D28: Effective CAC
A29: (none — CAC from the assumption row) | D29: =C29 -> 0

Sheet Founder
A1: Founder case
A3: Revenue per customer-month (ARPU₀) | B3: =Inputs!B5 -> 149
A4: Gross margin | B4: =Inputs!B6 -> 0.919
A5: Monthly churn | B5: =Inputs!B7 -> 0
A6: Monthly expansion | B6: =Inputs!B8 -> 0
A7: Blended CAC | B7: =Inputs!B11 -> 100
A8: Fixed burn / month | B8: =Inputs!B14*Inputs!B10+Inputs!B15 -> 6000
A9: New customers / month at full capacity | B9: =Inputs!B9 -> 2
A10: LTV (lifetime contribution, 60-mo cap) | B10: =B3*B4*(1-B5)^Inputs!B17*IF(ABS(1-(1-B5)*(1+B6))<0.000001,MAX(0,60-Inputs!B17),(1-((1-B5)*(1+B6))^MAX(0,60-Inputs!B17))/(1-(1-B5)*(1+B6))) -> 8078.929
A11: LTV / CAC (cash) | B11: =IF(B7>0,B10/B7,"n/a") -> 80.78929
A12: Payback (months, cumulative; "none" = not within 60) | B12: =IF(B3*B4<=0,"none",IF(B7<=0,1+Inputs!B17,IF((1-B5)*(1+B6)<=0,IF(B7<=B3*B4*(1-B5)^Inputs!B17,1+Inputs!B17,"none"),IF(ABS(1-(1-B5)*(1+B6))<0.000001,IF(B7/(B3*B4*(1-B5)^Inputs!B17)<=60-Inputs!B17,ROUNDUP(B7/(B3*B4*(1-B5)^Inputs!B17),0)+Inputs!B17,"none"),IF(1-B7*(1-(1-B5)*(1+B6))/(B3*B4*(1-B5)^Inputs!B17)<=0,"none",IF(ROUNDUP(LN(1-B7*(1-(1-B5)*(1+B6))/(B3*B4*(1-B5)^Inputs!B17))/LN((1-B5)*(1+B6)),0)<=60-Inputs!B17,ROUNDUP(LN(1-B7*(1-(1-B5)*(1+B6))/(B3*B4*(1-B5)^Inputs!B17))/LN((1-B5)*(1+B6)),0)+Inputs!B17,"none")))))) -> 2
A15: Month | B15: Ramp | C15: New customers (arrivals) | D15: Paying customers | E15: ARPU (derived) | F15: Revenue | G15: Gross profit | H15: Acquisition spend | I15: Fixed burn | J15: Net cash flow | K15: Cumulative cash | L15: Lowest net from here on
A16: 1 | B16: =IF(Inputs!B22=0,1,1/(1+EXP(-Inputs!B22*(A16-Inputs!B21)))) -> 0.5 | C16: =IF(A16-Inputs!B23<1,0,$B$9*IF(Inputs!B22=0,1,1/(1+EXP(-Inputs!B22*(A16-Inputs!B23-Inputs!B21))))) -> 1 | D16: =Inputs!B19*(1-$B$5)+IF(A16-Inputs!B17<1,0,OFFSET(C16,-Inputs!B17,0)*(1-$B$5)^Inputs!B17) -> 6 | E16: =IF(D16>0,F16/D16,0) -> 149 | F16: =Inputs!B20*(1-$B$5)*(1+$B$6)+IF(A16-Inputs!B17<1,0,OFFSET(C16,-Inputs!B17,0)*(1-$B$5)^Inputs!B17)*$B$3 -> 894 | G16: =F16*$B$4 -> 821.586 | H16: =$B$9*B16*$B$7 -> 100 | I16: =$B$8 -> 6000 | J16: =G16-H16-I16 -> -5278.414 | K16: =J16-Inputs!B16 -> -5278.414 | L16: =MIN(J16:J51) -> -5278.414
A17: 2 | B17: =IF(Inputs!B22=0,1,1/(1+EXP(-Inputs!B22*(A17-Inputs!B21)))) -> 0.73105858 | C17: =IF(A17-Inputs!B23<1,0,$B$9*IF(Inputs!B22=0,1,1/(1+EXP(-Inputs!B22*(A17-Inputs!B23-Inputs!B21))))) -> 1.4621172 | D17: =D16*(1-$B$5)+IF(A17-Inputs!B17<1,0,OFFSET(C17,-Inputs!B17,0)*(1-$B$5)^Inputs!B17) -> 7 | E17: =IF(D17>0,F17/D17,0) -> 149 | F17: =F16*(1-$B$5)*(1+$B$6)+IF(A17-Inputs!B17<1,0,OFFSET(C17,-Inputs!B17,0)*(1-$B$5)^Inputs!B17)*$B$3 -> 1043 | G17: =F17*$B$4 -> 958.517 | H17: =$B$9*B17*$B$7 -> 146.21172 | I17: =$B$8 -> 6000 | J17: =G17-H17-I17 -> -5187.6947 | K17: =K16+J17 -> -10466.109 | L17: =MIN(J17:J51) -> -5187.6947
A18: 3 | B18: =IF(Inputs!B22=0,1,1/(1+EXP(-Inputs!B22*(A18-Inputs!B21)))) -> 0.88079708 | C18: =IF(A18-Inputs!B23<1,0,$B$9*IF(Inputs!B22=0,1,1/(1+EXP(-Inputs!B22*(A18-Inputs!B23-Inputs!B21))))) -> 1.7615942 | D18: =D17*(1-$B$5)+IF(A18-Inputs!B17<1,0,OFFSET(C18,-Inputs!B17,0)*(1-$B$5)^Inputs!B17) -> 8.4621172 | E18: =IF(D18>0,F18/D18,0) -> 149 | F18: =F17*(1-$B$5)*(1+$B$6)+IF(A18-Inputs!B17<1,0,OFFSET(C18,-Inputs!B17,0)*(1-$B$5)^Inputs!B17)*$B$3 -> 1260.8555 | G18: =F18*$B$4 -> 1158.7262 | H18: =$B$9*B18*$B$7 -> 176.15942 | I18: =$B$8 -> 6000 | J18: =G18-H18-I18 -> -5017.4333 | K18: =K17+J18 -> -15483.542 | L18: =MIN(J18:J51) -> -5017.4333
A19: 4 | B19: =IF(Inputs!B22=0,1,1/(1+EXP(-Inputs!B22*(A19-Inputs!B21)))) -> 0.95257413 | C19: =IF(A19-Inputs!B23<1,0,$B$9*IF(Inputs!B22=0,1,1/(1+EXP(-Inputs!B22*(A19-Inputs!B23-Inputs!B21))))) -> 1.9051483 | D19: =D18*(1-$B$5)+IF(A19-Inputs!B17<1,0,OFFSET(C19,-Inputs!B17,0)*(1-$B$5)^Inputs!B17) -> 10.223711 | E19: =IF(D19>0,F19/D19,0) -> 149 | F19: =F18*(1-$B$5)*(1+$B$6)+IF(A19-Inputs!B17<1,0,OFFSET(C19,-Inputs!B17,0)*(1-$B$5)^Inputs!B17)*$B$3 -> 1523.333 | G19: =F19*$B$4 -> 1399.943 | H19: =$B$9*B19*$B$7 -> 190.51483 | I19: =$B$8 -> 6000 | J19: =G19-H19-I19 -> -4790.5718 | K19: =K18+J19 -> -20274.114 | L19: =MIN(J19:J51) -> -4790.5718
A20: 5 | B20: =IF(Inputs!B22=0,1,1/(1+EXP(-Inputs!B22*(A20-Inputs!B21)))) -> 0.98201379 | C20: =IF(A20-Inputs!B23<1,0,$B$9*IF(Inputs!B22=0,1,1/(1+EXP(-Inputs!B22*(A20-Inputs!B23-Inputs!B21))))) -> 1.9640276 | D20: =D19*(1-$B$5)+IF(A20-Inputs!B17<1,0,OFFSET(C20,-Inputs!B17,0)*(1-$B$5)^Inputs!B17) -> 12.12886 | E20: =IF(D20>0,F20/D20,0) -> 149 | F20: =F19*(1-$B$5)*(1+$B$6)+IF(A20-Inputs!B17<1,0,OFFSET(C20,-Inputs!B17,0)*(1-$B$5)^Inputs!B17)*$B$3 -> 1807.2001 | G20: =F20*$B$4 -> 1660.8169 | H20: =$B$9*B20*$B$7 -> 196.40276 | I20: =$B$8 -> 6000 | J20: =G20-H20-I20 -> -4535.5859 | K20: =K19+J20 -> -24809.7 | L20: =MIN(J20:J51) -> -4535.5859
A21: 6 | B21: =IF(Inputs!B22=0,1,1/(1+EXP(-Inputs!B22*(A21-Inputs!B21)))) -> 0.99330715 | C21: =IF(A21-Inputs!B23<1,0,$B$9*IF(Inputs!B22=0,1,1/(1+EXP(-Inputs!B22*(A21-Inputs!B23-Inputs!B21))))) -> 1.9866143 | D21: =D20*(1-$B$5)+IF(A21-Inputs!B17<1,0,OFFSET(C21,-Inputs!B17,0)*(1-$B$5)^Inputs!B17) -> 14.092887 | E21: =IF(D21>0,F21/D21,0) -> 149 | F21: =F20*(1-$B$5)*(1+$B$6)+IF(A21-Inputs!B17<1,0,OFFSET(C21,-Inputs!B17,0)*(1-$B$5)^Inputs!B17)*$B$3 -> 2099.8402 | G21: =F21*$B$4 -> 1929.7531 | H21: =$B$9*B21*$B$7 -> 198.66143 | I21: =$B$8 -> 6000 | J21: =G21-H21-I21 -> -4268.9083 | K21: =K20+J21 -> -29078.608 | L21: =MIN(J21:J51) -> -4268.9083
A22: 7 | B22: =IF(Inputs!B22=0,1,1/(1+EXP(-Inputs!B22*(A22-Inputs!B21)))) -> 0.99752738 | C22: =IF(A22-Inputs!B23<1,0,$B$9*IF(Inputs!B22=0,1,1/(1+EXP(-Inputs!B22*(A22-Inputs!B23-Inputs!B21))))) -> 1.9950548 | D22: =D21*(1-$B$5)+IF(A22-Inputs!B17<1,0,OFFSET(C22,-Inputs!B17,0)*(1-$B$5)^Inputs!B17) -> 16.079501 | E22: =IF(D22>0,F22/D22,0) -> 149 | F22: =F21*(1-$B$5)*(1+$B$6)+IF(A22-Inputs!B17<1,0,OFFSET(C22,-Inputs!B17,0)*(1-$B$5)^Inputs!B17)*$B$3 -> 2395.8457 | G22: =F22*$B$4 -> 2201.7822 | H22: =$B$9*B22*$B$7 -> 199.50548 | I22: =$B$8 -> 6000 | J22: =G22-H22-I22 -> -3997.7233 | K22: =K21+J22 -> -33076.331 | L22: =MIN(J22:J51) -> -3997.7233
A23: 8 | B23: =IF(Inputs!B22=0,1,1/(1+EXP(-Inputs!B22*(A23-Inputs!B21)))) -> 0.99908895 | C23: =IF(A23-Inputs!B23<1,0,$B$9*IF(Inputs!B22=0,1,1/(1+EXP(-Inputs!B22*(A23-Inputs!B23-Inputs!B21))))) -> 1.9981779 | D23: =D22*(1-$B$5)+IF(A23-Inputs!B17<1,0,OFFSET(C23,-Inputs!B17,0)*(1-$B$5)^Inputs!B17) -> 18.074556 | E23: =IF(D23>0,F23/D23,0) -> 149 | F23: =F22*(1-$B$5)*(1+$B$6)+IF(A23-Inputs!B17<1,0,OFFSET(C23,-Inputs!B17,0)*(1-$B$5)^Inputs!B17)*$B$3 -> 2693.1089 | G23: =F23*$B$4 -> 2474.9671 | H23: =$B$9*B23*$B$7 -> 199.81779 | I23: =$B$8 -> 6000 | J23: =G23-H23-I23 -> -3724.8507 | K23: =K22+J23 -> -36801.182 | L23: =MIN(J23:J51) -> -3724.8507
A24: 9 | B24: =IF(Inputs!B22=0,1,1/(1+EXP(-Inputs!B22*(A24-Inputs!B21)))) -> 0.99966465 | C24: =IF(A24-Inputs!B23<1,0,$B$9*IF(Inputs!B22=0,1,1/(1+EXP(-Inputs!B22*(A24-Inputs!B23-Inputs!B21))))) -> 1.9993293 | D24: =D23*(1-$B$5)+IF(A24-Inputs!B17<1,0,OFFSET(C24,-Inputs!B17,0)*(1-$B$5)^Inputs!B17) -> 20.072734 | E24: =IF(D24>0,F24/D24,0) -> 149 | F24: =F23*(1-$B$5)*(1+$B$6)+IF(A24-Inputs!B17<1,0,OFFSET(C24,-Inputs!B17,0)*(1-$B$5)^Inputs!B17)*$B$3 -> 2990.8374 | G24: =F24*$B$4 -> 2748.5796 | H24: =$B$9*B24*$B$7 -> 199.93293 | I24: =$B$8 -> 6000 | J24: =G24-H24-I24 -> -3451.3534 | K24: =K23+J24 -> -40252.535 | L24: =MIN(J24:J51) -> -3451.3534
A25: 10 | B25: =IF(Inputs!B22=0,1,1/(1+EXP(-Inputs!B22*(A25-Inputs!B21)))) -> 0.99987661 | C25: =IF(A25-Inputs!B23<1,0,$B$9*IF(Inputs!B22=0,1,1/(1+EXP(-Inputs!B22*(A25-Inputs!B23-Inputs!B21))))) -> 1.9997532 | D25: =D24*(1-$B$5)+IF(A25-Inputs!B17<1,0,OFFSET(C25,-Inputs!B17,0)*(1-$B$5)^Inputs!B17) -> 22.072063 | E25: =IF(D25>0,F25/D25,0) -> 149 | F25: =F24*(1-$B$5)*(1+$B$6)+IF(A25-Inputs!B17<1,0,OFFSET(C25,-Inputs!B17,0)*(1-$B$5)^Inputs!B17)*$B$3 -> 3288.7374 | G25: =F25*$B$4 -> 3022.3497 | H25: =$B$9*B25*$B$7 -> 199.97532 | I25: =$B$8 -> 6000 | J25: =G25-H25-I25 -> -3177.6256 | K25: =K24+J25 -> -43430.161 | L25: =MIN(J25:J51) -> -3177.6256
A26: 11 | B26: =IF(Inputs!B22=0,1,1/(1+EXP(-Inputs!B22*(A26-Inputs!B21)))) -> 0.9999546 | C26: =IF(A26-Inputs!B23<1,0,$B$9*IF(Inputs!B22=0,1,1/(1+EXP(-Inputs!B22*(A26-Inputs!B23-Inputs!B21))))) -> 1.9999092 | D26: =D25*(1-$B$5)+IF(A26-Inputs!B17<1,0,OFFSET(C26,-Inputs!B17,0)*(1-$B$5)^Inputs!B17) -> 24.071817 | E26: =IF(D26>0,F26/D26,0) -> 149 | F26: =F25*(1-$B$5)*(1+$B$6)+IF(A26-Inputs!B17<1,0,OFFSET(C26,-Inputs!B17,0)*(1-$B$5)^Inputs!B17)*$B$3 -> 3586.7007 | G26: =F26*$B$4 -> 3296.1779 | H26: =$B$9*B26*$B$7 -> 199.99092 | I26: =$B$8 -> 6000 | J26: =G26-H26-I26 -> -2903.813 | K26: =K25+J26 -> -46333.974 | L26: =MIN(J26:J51) -> -2903.813
A27: 12 | B27: =IF(Inputs!B22=0,1,1/(1+EXP(-Inputs!B22*(A27-Inputs!B21)))) -> 0.9999833 | C27: =IF(A27-Inputs!B23<1,0,$B$9*IF(Inputs!B22=0,1,1/(1+EXP(-Inputs!B22*(A27-Inputs!B23-Inputs!B21))))) -> 1.9999666 | D27: =D26*(1-$B$5)+IF(A27-Inputs!B17<1,0,OFFSET(C27,-Inputs!B17,0)*(1-$B$5)^Inputs!B17) -> 26.071726 | E27: =IF(D27>0,F27/D27,0) -> 149 | F27: =F26*(1-$B$5)*(1+$B$6)+IF(A27-Inputs!B17<1,0,OFFSET(C27,-Inputs!B17,0)*(1-$B$5)^Inputs!B17)*$B$3 -> 3884.6871 | G27: =F27*$B$4 -> 3570.0275 | H27: =$B$9*B27*$B$7 -> 199.99666 | I27: =$B$8 -> 6000 | J27: =G27-H27-I27 -> -2629.9692 | K27: =K26+J27 -> -48963.943 | L27: =MIN(J27:J51) -> -2629.9692
A28: 13 | B28: =IF(Inputs!B22=0,1,1/(1+EXP(-Inputs!B22*(A28-Inputs!B21)))) -> 0.99999386 | C28: =IF(A28-Inputs!B23<1,0,$B$9*IF(Inputs!B22=0,1,1/(1+EXP(-Inputs!B22*(A28-Inputs!B23-Inputs!B21))))) -> 1.9999877 | D28: =D27*(1-$B$5)+IF(A28-Inputs!B17<1,0,OFFSET(C28,-Inputs!B17,0)*(1-$B$5)^Inputs!B17) -> 28.071692 | E28: =IF(D28>0,F28/D28,0) -> 149 | F28: =F27*(1-$B$5)*(1+$B$6)+IF(A28-Inputs!B17<1,0,OFFSET(C28,-Inputs!B17,0)*(1-$B$5)^Inputs!B17)*$B$3 -> 4182.6822 | G28: =F28*$B$4 -> 3843.8849 | H28: =$B$9*B28*$B$7 -> 199.99877 | I28: =$B$8 -> 6000 | J28: =G28-H28-I28 -> -2356.1139 | K28: =K27+J28 -> -51320.057 | L28: =MIN(J28:J51) -> -2356.1139
A29: 14 | B29: =IF(Inputs!B22=0,1,1/(1+EXP(-Inputs!B22*(A29-Inputs!B21)))) -> 0.99999774 | C29: =IF(A29-Inputs!B23<1,0,$B$9*IF(Inputs!B22=0,1,1/(1+EXP(-Inputs!B22*(A29-Inputs!B23-Inputs!B21))))) -> 1.9999955 | D29: =D28*(1-$B$5)+IF(A29-Inputs!B17<1,0,OFFSET(C29,-Inputs!B17,0)*(1-$B$5)^Inputs!B17) -> 30.07168 | E29: =IF(D29>0,F29/D29,0) -> 149 | F29: =F28*(1-$B$5)*(1+$B$6)+IF(A29-Inputs!B17<1,0,OFFSET(C29,-Inputs!B17,0)*(1-$B$5)^Inputs!B17)*$B$3 -> 4480.6803 | G29: =F29*$B$4 -> 4117.7452 | H29: =$B$9*B29*$B$7 -> 199.99955 | I29: =$B$8 -> 6000 | J29: =G29-H29-I29 -> -2082.2543 | K29: =K28+J29 -> -53402.311 | L29: =MIN(J29:J51) -> -2082.2543
A30: 15 | B30: =IF(Inputs!B22=0,1,1/(1+EXP(-Inputs!B22*(A30-Inputs!B21)))) -> 0.99999917 | C30: =IF(A30-Inputs!B23<1,0,$B$9*IF(Inputs!B22=0,1,1/(1+EXP(-Inputs!B22*(A30-Inputs!B23-Inputs!B21))))) -> 1.9999983 | D30: =D29*(1-$B$5)+IF(A30-Inputs!B17<1,0,OFFSET(C30,-Inputs!B17,0)*(1-$B$5)^Inputs!B17) -> 32.071676 | E30: =IF(D30>0,F30/D30,0) -> 149 | F30: =F29*(1-$B$5)*(1+$B$6)+IF(A30-Inputs!B17<1,0,OFFSET(C30,-Inputs!B17,0)*(1-$B$5)^Inputs!B17)*$B$3 -> 4778.6797 | G30: =F30*$B$4 -> 4391.6066 | H30: =$B$9*B30*$B$7 -> 199.99983 | I30: =$B$8 -> 6000 | J30: =G30-H30-I30 -> -1808.3932 | K30: =K29+J30 -> -55210.705 | L30: =MIN(J30:J51) -> -1808.3932
A31: 16 | B31: =IF(Inputs!B22=0,1,1/(1+EXP(-Inputs!B22*(A31-Inputs!B21)))) -> 0.99999969 | C31: =IF(A31-Inputs!B23<1,0,$B$9*IF(Inputs!B22=0,1,1/(1+EXP(-Inputs!B22*(A31-Inputs!B23-Inputs!B21))))) -> 1.9999994 | D31: =D30*(1-$B$5)+IF(A31-Inputs!B17<1,0,OFFSET(C31,-Inputs!B17,0)*(1-$B$5)^Inputs!B17) -> 34.071674 | E31: =IF(D31>0,F31/D31,0) -> 149 | F31: =F30*(1-$B$5)*(1+$B$6)+IF(A31-Inputs!B17<1,0,OFFSET(C31,-Inputs!B17,0)*(1-$B$5)^Inputs!B17)*$B$3 -> 5076.6794 | G31: =F31*$B$4 -> 4665.4684 | H31: =$B$9*B31*$B$7 -> 199.99994 | I31: =$B$8 -> 6000 | J31: =G31-H31-I31 -> -1534.5316 | K31: =K30+J31 -> -56745.236 | L31: =MIN(J31:J51) -> -1534.5316
A32: 17 | B32: =IF(Inputs!B22=0,1,1/(1+EXP(-Inputs!B22*(A32-Inputs!B21)))) -> 0.99999989 | C32: =IF(A32-Inputs!B23<1,0,$B$9*IF(Inputs!B22=0,1,1/(1+EXP(-Inputs!B22*(A32-Inputs!B23-Inputs!B21))))) -> 1.9999998 | D32: =D31*(1-$B$5)+IF(A32-Inputs!B17<1,0,OFFSET(C32,-Inputs!B17,0)*(1-$B$5)^Inputs!B17) -> 36.071673 | E32: =IF(D32>0,F32/D32,0) -> 149 | F32: =F31*(1-$B$5)*(1+$B$6)+IF(A32-Inputs!B17<1,0,OFFSET(C32,-Inputs!B17,0)*(1-$B$5)^Inputs!B17)*$B$3 -> 5374.6793 | G32: =F32*$B$4 -> 4939.3303 | H32: =$B$9*B32*$B$7 -> 199.99998 | I32: =$B$8 -> 6000 | J32: =G32-H32-I32 -> -1260.6697 | K32: =K31+J32 -> -58005.906 | L32: =MIN(J32:J51) -> -1260.6697
A33: 18 | B33: =IF(Inputs!B22=0,1,1/(1+EXP(-Inputs!B22*(A33-Inputs!B21)))) -> 0.99999996 | C33: =IF(A33-Inputs!B23<1,0,$B$9*IF(Inputs!B22=0,1,1/(1+EXP(-Inputs!B22*(A33-Inputs!B23-Inputs!B21))))) -> 1.9999999 | D33: =D32*(1-$B$5)+IF(A33-Inputs!B17<1,0,OFFSET(C33,-Inputs!B17,0)*(1-$B$5)^Inputs!B17) -> 38.071673 | E33: =IF(D33>0,F33/D33,0) -> 149 | F33: =F32*(1-$B$5)*(1+$B$6)+IF(A33-Inputs!B17<1,0,OFFSET(C33,-Inputs!B17,0)*(1-$B$5)^Inputs!B17)*$B$3 -> 5672.6793 | G33: =F33*$B$4 -> 5213.1923 | H33: =$B$9*B33*$B$7 -> 199.99999 | I33: =$B$8 -> 6000 | J33: =G33-H33-I33 -> -986.80772 | K33: =K32+J33 -> -58992.713 | L33: =MIN(J33:J51) -> -986.80772
A34: 19 | B34: =IF(Inputs!B22=0,1,1/(1+EXP(-Inputs!B22*(A34-Inputs!B21)))) -> 0.99999998 | C34: =IF(A34-Inputs!B23<1,0,$B$9*IF(Inputs!B22=0,1,1/(1+EXP(-Inputs!B22*(A34-Inputs!B23-Inputs!B21))))) -> 2 | D34: =D33*(1-$B$5)+IF(A34-Inputs!B17<1,0,OFFSET(C34,-Inputs!B17,0)*(1-$B$5)^Inputs!B17) -> 40.071673 | E34: =IF(D34>0,F34/D34,0) -> 149 | F34: =F33*(1-$B$5)*(1+$B$6)+IF(A34-Inputs!B17<1,0,OFFSET(C34,-Inputs!B17,0)*(1-$B$5)^Inputs!B17)*$B$3 -> 5970.6793 | G34: =F34*$B$4 -> 5487.0543 | H34: =$B$9*B34*$B$7 -> 200 | I34: =$B$8 -> 6000 | J34: =G34-H34-I34 -> -712.94574 | K34: =K33+J34 -> -59705.659 | L34: =MIN(J34:J51) -> -712.94574
A35: 20 | B35: =IF(Inputs!B22=0,1,1/(1+EXP(-Inputs!B22*(A35-Inputs!B21)))) -> 0.99999999 | C35: =IF(A35-Inputs!B23<1,0,$B$9*IF(Inputs!B22=0,1,1/(1+EXP(-Inputs!B22*(A35-Inputs!B23-Inputs!B21))))) -> 2 | D35: =D34*(1-$B$5)+IF(A35-Inputs!B17<1,0,OFFSET(C35,-Inputs!B17,0)*(1-$B$5)^Inputs!B17) -> 42.071673 | E35: =IF(D35>0,F35/D35,0) -> 149 | F35: =F34*(1-$B$5)*(1+$B$6)+IF(A35-Inputs!B17<1,0,OFFSET(C35,-Inputs!B17,0)*(1-$B$5)^Inputs!B17)*$B$3 -> 6268.6793 | G35: =F35*$B$4 -> 5760.9163 | H35: =$B$9*B35*$B$7 -> 200 | I35: =$B$8 -> 6000 | J35: =G35-H35-I35 -> -439.08375 | K35: =K34+J35 -> -60144.743 | L35: =MIN(J35:J51) -> -439.08375
A36: 21 | B36: =IF(Inputs!B22=0,1,1/(1+EXP(-Inputs!B22*(A36-Inputs!B21)))) -> 1 | C36: =IF(A36-Inputs!B23<1,0,$B$9*IF(Inputs!B22=0,1,1/(1+EXP(-Inputs!B22*(A36-Inputs!B23-Inputs!B21))))) -> 2 | D36: =D35*(1-$B$5)+IF(A36-Inputs!B17<1,0,OFFSET(C36,-Inputs!B17,0)*(1-$B$5)^Inputs!B17) -> 44.071673 | E36: =IF(D36>0,F36/D36,0) -> 149 | F36: =F35*(1-$B$5)*(1+$B$6)+IF(A36-Inputs!B17<1,0,OFFSET(C36,-Inputs!B17,0)*(1-$B$5)^Inputs!B17)*$B$3 -> 6566.6793 | G36: =F36*$B$4 -> 6034.7783 | H36: =$B$9*B36*$B$7 -> 200 | I36: =$B$8 -> 6000 | J36: =G36-H36-I36 -> -165.22175 | K36: =K35+J36 -> -60309.965 | L36: =MIN(J36:J51) -> -165.22175
A37: 22 | B37: =IF(Inputs!B22=0,1,1/(1+EXP(-Inputs!B22*(A37-Inputs!B21)))) -> 1 | C37: =IF(A37-Inputs!B23<1,0,$B$9*IF(Inputs!B22=0,1,1/(1+EXP(-Inputs!B22*(A37-Inputs!B23-Inputs!B21))))) -> 2 | D37: =D36*(1-$B$5)+IF(A37-Inputs!B17<1,0,OFFSET(C37,-Inputs!B17,0)*(1-$B$5)^Inputs!B17) -> 46.071673 | E37: =IF(D37>0,F37/D37,0) -> 149 | F37: =F36*(1-$B$5)*(1+$B$6)+IF(A37-Inputs!B17<1,0,OFFSET(C37,-Inputs!B17,0)*(1-$B$5)^Inputs!B17)*$B$3 -> 6864.6793 | G37: =F37*$B$4 -> 6308.6403 | H37: =$B$9*B37*$B$7 -> 200 | I37: =$B$8 -> 6000 | J37: =G37-H37-I37 -> 108.64025 | K37: =K36+J37 -> -60201.324 | L37: =MIN(J37:J51) -> 108.64025
A38: 23 | B38: =IF(Inputs!B22=0,1,1/(1+EXP(-Inputs!B22*(A38-Inputs!B21)))) -> 1 | C38: =IF(A38-Inputs!B23<1,0,$B$9*IF(Inputs!B22=0,1,1/(1+EXP(-Inputs!B22*(A38-Inputs!B23-Inputs!B21))))) -> 2 | D38: =D37*(1-$B$5)+IF(A38-Inputs!B17<1,0,OFFSET(C38,-Inputs!B17,0)*(1-$B$5)^Inputs!B17) -> 48.071673 | E38: =IF(D38>0,F38/D38,0) -> 149 | F38: =F37*(1-$B$5)*(1+$B$6)+IF(A38-Inputs!B17<1,0,OFFSET(C38,-Inputs!B17,0)*(1-$B$5)^Inputs!B17)*$B$3 -> 7162.6793 | G38: =F38*$B$4 -> 6582.5023 | H38: =$B$9*B38*$B$7 -> 200 | I38: =$B$8 -> 6000 | J38: =G38-H38-I38 -> 382.50225 | K38: =K37+J38 -> -59818.822 | L38: =MIN(J38:J51) -> 382.50225
A39: 24 | B39: =IF(Inputs!B22=0,1,1/(1+EXP(-Inputs!B22*(A39-Inputs!B21)))) -> 1 | C39: =IF(A39-Inputs!B23<1,0,$B$9*IF(Inputs!B22=0,1,1/(1+EXP(-Inputs!B22*(A39-Inputs!B23-Inputs!B21))))) -> 2 | D39: =D38*(1-$B$5)+IF(A39-Inputs!B17<1,0,OFFSET(C39,-Inputs!B17,0)*(1-$B$5)^Inputs!B17) -> 50.071673 | E39: =IF(D39>0,F39/D39,0) -> 149 | F39: =F38*(1-$B$5)*(1+$B$6)+IF(A39-Inputs!B17<1,0,OFFSET(C39,-Inputs!B17,0)*(1-$B$5)^Inputs!B17)*$B$3 -> 7460.6793 | G39: =F39*$B$4 -> 6856.3643 | H39: =$B$9*B39*$B$7 -> 200 | I39: =$B$8 -> 6000 | J39: =G39-H39-I39 -> 656.36425 | K39: =K38+J39 -> -59162.458 | L39: =MIN(J39:J51) -> 656.36425
A40: 25 | B40: =IF(Inputs!B22=0,1,1/(1+EXP(-Inputs!B22*(A40-Inputs!B21)))) -> 1 | C40: =IF(A40-Inputs!B23<1,0,$B$9*IF(Inputs!B22=0,1,1/(1+EXP(-Inputs!B22*(A40-Inputs!B23-Inputs!B21))))) -> 2 | D40: =D39*(1-$B$5)+IF(A40-Inputs!B17<1,0,OFFSET(C40,-Inputs!B17,0)*(1-$B$5)^Inputs!B17) -> 52.071673 | E40: =IF(D40>0,F40/D40,0) -> 149 | F40: =F39*(1-$B$5)*(1+$B$6)+IF(A40-Inputs!B17<1,0,OFFSET(C40,-Inputs!B17,0)*(1-$B$5)^Inputs!B17)*$B$3 -> 7758.6793 | G40: =F40*$B$4 -> 7130.2263 | H40: =$B$9*B40*$B$7 -> 200 | I40: =$B$8 -> 6000 | J40: =G40-H40-I40 -> 930.22625 | K40: =K39+J40 -> -58232.232 | L40: =MIN(J40:J51) -> 930.22625
A41: 26 | B41: =IF(Inputs!B22=0,1,1/(1+EXP(-Inputs!B22*(A41-Inputs!B21)))) -> 1 | C41: =IF(A41-Inputs!B23<1,0,$B$9*IF(Inputs!B22=0,1,1/(1+EXP(-Inputs!B22*(A41-Inputs!B23-Inputs!B21))))) -> 2 | D41: =D40*(1-$B$5)+IF(A41-Inputs!B17<1,0,OFFSET(C41,-Inputs!B17,0)*(1-$B$5)^Inputs!B17) -> 54.071673 | E41: =IF(D41>0,F41/D41,0) -> 149 | F41: =F40*(1-$B$5)*(1+$B$6)+IF(A41-Inputs!B17<1,0,OFFSET(C41,-Inputs!B17,0)*(1-$B$5)^Inputs!B17)*$B$3 -> 8056.6793 | G41: =F41*$B$4 -> 7404.0883 | H41: =$B$9*B41*$B$7 -> 200 | I41: =$B$8 -> 6000 | J41: =G41-H41-I41 -> 1204.0883 | K41: =K40+J41 -> -57028.143 | L41: =MIN(J41:J51) -> 1204.0883
A42: 27 | B42: =IF(Inputs!B22=0,1,1/(1+EXP(-Inputs!B22*(A42-Inputs!B21)))) -> 1 | C42: =IF(A42-Inputs!B23<1,0,$B$9*IF(Inputs!B22=0,1,1/(1+EXP(-Inputs!B22*(A42-Inputs!B23-Inputs!B21))))) -> 2 | D42: =D41*(1-$B$5)+IF(A42-Inputs!B17<1,0,OFFSET(C42,-Inputs!B17,0)*(1-$B$5)^Inputs!B17) -> 56.071673 | E42: =IF(D42>0,F42/D42,0) -> 149 | F42: =F41*(1-$B$5)*(1+$B$6)+IF(A42-Inputs!B17<1,0,OFFSET(C42,-Inputs!B17,0)*(1-$B$5)^Inputs!B17)*$B$3 -> 8354.6793 | G42: =F42*$B$4 -> 7677.9503 | H42: =$B$9*B42*$B$7 -> 200 | I42: =$B$8 -> 6000 | J42: =G42-H42-I42 -> 1477.9503 | K42: =K41+J42 -> -55550.193 | L42: =MIN(J42:J51) -> 1477.9503
A43: 28 | B43: =IF(Inputs!B22=0,1,1/(1+EXP(-Inputs!B22*(A43-Inputs!B21)))) -> 1 | C43: =IF(A43-Inputs!B23<1,0,$B$9*IF(Inputs!B22=0,1,1/(1+EXP(-Inputs!B22*(A43-Inputs!B23-Inputs!B21))))) -> 2 | D43: =D42*(1-$B$5)+IF(A43-Inputs!B17<1,0,OFFSET(C43,-Inputs!B17,0)*(1-$B$5)^Inputs!B17) -> 58.071673 | E43: =IF(D43>0,F43/D43,0) -> 149 | F43: =F42*(1-$B$5)*(1+$B$6)+IF(A43-Inputs!B17<1,0,OFFSET(C43,-Inputs!B17,0)*(1-$B$5)^Inputs!B17)*$B$3 -> 8652.6793 | G43: =F43*$B$4 -> 7951.8123 | H43: =$B$9*B43*$B$7 -> 200 | I43: =$B$8 -> 6000 | J43: =G43-H43-I43 -> 1751.8123 | K43: =K42+J43 -> -53798.381 | L43: =MIN(J43:J51) -> 1751.8123
A44: 29 | B44: =IF(Inputs!B22=0,1,1/(1+EXP(-Inputs!B22*(A44-Inputs!B21)))) -> 1 | C44: =IF(A44-Inputs!B23<1,0,$B$9*IF(Inputs!B22=0,1,1/(1+EXP(-Inputs!B22*(A44-Inputs!B23-Inputs!B21))))) -> 2 | D44: =D43*(1-$B$5)+IF(A44-Inputs!B17<1,0,OFFSET(C44,-Inputs!B17,0)*(1-$B$5)^Inputs!B17) -> 60.071673 | E44: =IF(D44>0,F44/D44,0) -> 149 | F44: =F43*(1-$B$5)*(1+$B$6)+IF(A44-Inputs!B17<1,0,OFFSET(C44,-Inputs!B17,0)*(1-$B$5)^Inputs!B17)*$B$3 -> 8950.6793 | G44: =F44*$B$4 -> 8225.6743 | H44: =$B$9*B44*$B$7 -> 200 | I44: =$B$8 -> 6000 | J44: =G44-H44-I44 -> 2025.6743 | K44: =K43+J44 -> -51772.707 | L44: =MIN(J44:J51) -> 2025.6743
A45: 30 | B45: =IF(Inputs!B22=0,1,1/(1+EXP(-Inputs!B22*(A45-Inputs!B21)))) -> 1 | C45: =IF(A45-Inputs!B23<1,0,$B$9*IF(Inputs!B22=0,1,1/(1+EXP(-Inputs!B22*(A45-Inputs!B23-Inputs!B21))))) -> 2 | D45: =D44*(1-$B$5)+IF(A45-Inputs!B17<1,0,OFFSET(C45,-Inputs!B17,0)*(1-$B$5)^Inputs!B17) -> 62.071673 | E45: =IF(D45>0,F45/D45,0) -> 149 | F45: =F44*(1-$B$5)*(1+$B$6)+IF(A45-Inputs!B17<1,0,OFFSET(C45,-Inputs!B17,0)*(1-$B$5)^Inputs!B17)*$B$3 -> 9248.6793 | G45: =F45*$B$4 -> 8499.5363 | H45: =$B$9*B45*$B$7 -> 200 | I45: =$B$8 -> 6000 | J45: =G45-H45-I45 -> 2299.5363 | K45: =K44+J45 -> -49473.17 | L45: =MIN(J45:J51) -> 2299.5363
A46: 31 | B46: =IF(Inputs!B22=0,1,1/(1+EXP(-Inputs!B22*(A46-Inputs!B21)))) -> 1 | C46: =IF(A46-Inputs!B23<1,0,$B$9*IF(Inputs!B22=0,1,1/(1+EXP(-Inputs!B22*(A46-Inputs!B23-Inputs!B21))))) -> 2 | D46: =D45*(1-$B$5)+IF(A46-Inputs!B17<1,0,OFFSET(C46,-Inputs!B17,0)*(1-$B$5)^Inputs!B17) -> 64.071673 | E46: =IF(D46>0,F46/D46,0) -> 149 | F46: =F45*(1-$B$5)*(1+$B$6)+IF(A46-Inputs!B17<1,0,OFFSET(C46,-Inputs!B17,0)*(1-$B$5)^Inputs!B17)*$B$3 -> 9546.6793 | G46: =F46*$B$4 -> 8773.3983 | H46: =$B$9*B46*$B$7 -> 200 | I46: =$B$8 -> 6000 | J46: =G46-H46-I46 -> 2573.3983 | K46: =K45+J46 -> -46899.772 | L46: =MIN(J46:J51) -> 2573.3983
A47: 32 | B47: =IF(Inputs!B22=0,1,1/(1+EXP(-Inputs!B22*(A47-Inputs!B21)))) -> 1 | C47: =IF(A47-Inputs!B23<1,0,$B$9*IF(Inputs!B22=0,1,1/(1+EXP(-Inputs!B22*(A47-Inputs!B23-Inputs!B21))))) -> 2 | D47: =D46*(1-$B$5)+IF(A47-Inputs!B17<1,0,OFFSET(C47,-Inputs!B17,0)*(1-$B$5)^Inputs!B17) -> 66.071673 | E47: =IF(D47>0,F47/D47,0) -> 149 | F47: =F46*(1-$B$5)*(1+$B$6)+IF(A47-Inputs!B17<1,0,OFFSET(C47,-Inputs!B17,0)*(1-$B$5)^Inputs!B17)*$B$3 -> 9844.6793 | G47: =F47*$B$4 -> 9047.2603 | H47: =$B$9*B47*$B$7 -> 200 | I47: =$B$8 -> 6000 | J47: =G47-H47-I47 -> 2847.2603 | K47: =K46+J47 -> -44052.512 | L47: =MIN(J47:J51) -> 2847.2603
A48: 33 | B48: =IF(Inputs!B22=0,1,1/(1+EXP(-Inputs!B22*(A48-Inputs!B21)))) -> 1 | C48: =IF(A48-Inputs!B23<1,0,$B$9*IF(Inputs!B22=0,1,1/(1+EXP(-Inputs!B22*(A48-Inputs!B23-Inputs!B21))))) -> 2 | D48: =D47*(1-$B$5)+IF(A48-Inputs!B17<1,0,OFFSET(C48,-Inputs!B17,0)*(1-$B$5)^Inputs!B17) -> 68.071673 | E48: =IF(D48>0,F48/D48,0) -> 149 | F48: =F47*(1-$B$5)*(1+$B$6)+IF(A48-Inputs!B17<1,0,OFFSET(C48,-Inputs!B17,0)*(1-$B$5)^Inputs!B17)*$B$3 -> 10142.679 | G48: =F48*$B$4 -> 9321.1223 | H48: =$B$9*B48*$B$7 -> 200 | I48: =$B$8 -> 6000 | J48: =G48-H48-I48 -> 3121.1223 | K48: =K47+J48 -> -40931.39 | L48: =MIN(J48:J51) -> 3121.1223
A49: 34 | B49: =IF(Inputs!B22=0,1,1/(1+EXP(-Inputs!B22*(A49-Inputs!B21)))) -> 1 | C49: =IF(A49-Inputs!B23<1,0,$B$9*IF(Inputs!B22=0,1,1/(1+EXP(-Inputs!B22*(A49-Inputs!B23-Inputs!B21))))) -> 2 | D49: =D48*(1-$B$5)+IF(A49-Inputs!B17<1,0,OFFSET(C49,-Inputs!B17,0)*(1-$B$5)^Inputs!B17) -> 70.071673 | E49: =IF(D49>0,F49/D49,0) -> 149 | F49: =F48*(1-$B$5)*(1+$B$6)+IF(A49-Inputs!B17<1,0,OFFSET(C49,-Inputs!B17,0)*(1-$B$5)^Inputs!B17)*$B$3 -> 10440.679 | G49: =F49*$B$4 -> 9594.9843 | H49: =$B$9*B49*$B$7 -> 200 | I49: =$B$8 -> 6000 | J49: =G49-H49-I49 -> 3394.9843 | K49: =K48+J49 -> -37536.405 | L49: =MIN(J49:J51) -> 3394.9843
A50: 35 | B50: =IF(Inputs!B22=0,1,1/(1+EXP(-Inputs!B22*(A50-Inputs!B21)))) -> 1 | C50: =IF(A50-Inputs!B23<1,0,$B$9*IF(Inputs!B22=0,1,1/(1+EXP(-Inputs!B22*(A50-Inputs!B23-Inputs!B21))))) -> 2 | D50: =D49*(1-$B$5)+IF(A50-Inputs!B17<1,0,OFFSET(C50,-Inputs!B17,0)*(1-$B$5)^Inputs!B17) -> 72.071673 | E50: =IF(D50>0,F50/D50,0) -> 149 | F50: =F49*(1-$B$5)*(1+$B$6)+IF(A50-Inputs!B17<1,0,OFFSET(C50,-Inputs!B17,0)*(1-$B$5)^Inputs!B17)*$B$3 -> 10738.679 | G50: =F50*$B$4 -> 9868.8463 | H50: =$B$9*B50*$B$7 -> 200 | I50: =$B$8 -> 6000 | J50: =G50-H50-I50 -> 3668.8463 | K50: =K49+J50 -> -33867.559 | L50: =MIN(J50:J51) -> 3668.8463
A51: 36 | B51: =IF(Inputs!B22=0,1,1/(1+EXP(-Inputs!B22*(A51-Inputs!B21)))) -> 1 | C51: =IF(A51-Inputs!B23<1,0,$B$9*IF(Inputs!B22=0,1,1/(1+EXP(-Inputs!B22*(A51-Inputs!B23-Inputs!B21))))) -> 2 | D51: =D50*(1-$B$5)+IF(A51-Inputs!B17<1,0,OFFSET(C51,-Inputs!B17,0)*(1-$B$5)^Inputs!B17) -> 74.071673 | E51: =IF(D51>0,F51/D51,0) -> 149 | F51: =F50*(1-$B$5)*(1+$B$6)+IF(A51-Inputs!B17<1,0,OFFSET(C51,-Inputs!B17,0)*(1-$B$5)^Inputs!B17)*$B$3 -> 11036.679 | G51: =F51*$B$4 -> 10142.708 | H51: =$B$9*B51*$B$7 -> 200 | I51: =$B$8 -> 6000 | J51: =G51-H51-I51 -> 3942.7083 | K51: =K50+J51 -> -29924.851 | L51: =MIN(J51) -> 3942.7083
A53: Break-even month (net ≥ 0 from then on) | B53: =IFERROR(INDEX(A16:A51,MATCH(TRUE(),INDEX(L16:L51>=0,0),0)),"none") -> 22
A54: Peak capital need | B54: =MAX(0,Inputs!B16,-MIN(K16:K51)) -> 60309.965
A55: Reference customers, 3y (segment × comparable penetration) | B55: =Inputs!B24*Inputs!B25 -> 75.36
A56: Bottom-up customers, month 36 (same 3-year window as the reference) | B56: =D51 -> 74.071673
A57: Ratio to reference | B57: =IF(B55>0,B56/B55,0) -> 0.98290437
A58: Position | B58: =IF(B57>1,"above_comparables",IF(B57<0.1,"far_below_comparables","within_range")) -> within_range

Sheet Market
A1: Market case
A3: Revenue per customer-month (ARPU₀) | B3: =Inputs!C5 -> 134
A4: Gross margin | B4: =Inputs!C6 -> 0.8
A5: Monthly churn | B5: =Inputs!C7 -> 0.05
A6: Monthly expansion | B6: =Inputs!C8 -> 0
A7: Blended CAC | B7: =Inputs!C11 -> 100
A8: Fixed burn / month | B8: =Inputs!B14*Inputs!C10+Inputs!B15 -> 11970
A9: New customers / month at full capacity | B9: =Inputs!C9 -> 1.8
A10: LTV (lifetime contribution, 60-mo cap) | B10: =B3*B4*(1-B5)^Inputs!B17*IF(ABS(1-(1-B5)*(1+B6))<0.000001,MAX(0,60-Inputs!B17),(1-((1-B5)*(1+B6))^MAX(0,60-Inputs!B17))/(1-(1-B5)*(1+B6))) -> 1938.0264
A11: LTV / CAC (cash) | B11: =IF(B7>0,B10/B7,"n/a") -> 19.380264
A12: Payback (months, cumulative; "none" = not within 60) | B12: =IF(B3*B4<=0,"none",IF(B7<=0,1+Inputs!B17,IF((1-B5)*(1+B6)<=0,IF(B7<=B3*B4*(1-B5)^Inputs!B17,1+Inputs!B17,"none"),IF(ABS(1-(1-B5)*(1+B6))<0.000001,IF(B7/(B3*B4*(1-B5)^Inputs!B17)<=60-Inputs!B17,ROUNDUP(B7/(B3*B4*(1-B5)^Inputs!B17),0)+Inputs!B17,"none"),IF(1-B7*(1-(1-B5)*(1+B6))/(B3*B4*(1-B5)^Inputs!B17)<=0,"none",IF(ROUNDUP(LN(1-B7*(1-(1-B5)*(1+B6))/(B3*B4*(1-B5)^Inputs!B17))/LN((1-B5)*(1+B6)),0)<=60-Inputs!B17,ROUNDUP(LN(1-B7*(1-(1-B5)*(1+B6))/(B3*B4*(1-B5)^Inputs!B17))/LN((1-B5)*(1+B6)),0)+Inputs!B17,"none")))))) -> 2
A15: Month | B15: Ramp | C15: New customers (arrivals) | D15: Paying customers | E15: ARPU (derived) | F15: Revenue | G15: Gross profit | H15: Acquisition spend | I15: Fixed burn | J15: Net cash flow | K15: Cumulative cash | L15: Lowest net from here on
A16: 1 | B16: =IF(Inputs!B22=0,1,1/(1+EXP(-Inputs!B22*(A16-Inputs!B21)))) -> 0.5 | C16: =IF(A16-Inputs!B23<1,0,$B$9*IF(Inputs!B22=0,1,1/(1+EXP(-Inputs!B22*(A16-Inputs!B23-Inputs!B21))))) -> 0.9 | D16: =Inputs!B19*(1-$B$5)+IF(A16-Inputs!B17<1,0,OFFSET(C16,-Inputs!B17,0)*(1-$B$5)^Inputs!B17) -> 5.7 | E16: =IF(D16>0,F16/D16,0) -> 149 | F16: =Inputs!B20*(1-$B$5)*(1+$B$6)+IF(A16-Inputs!B17<1,0,OFFSET(C16,-Inputs!B17,0)*(1-$B$5)^Inputs!B17)*$B$3 -> 849.3 | G16: =F16*$B$4 -> 679.44 | H16: =$B$9*B16*$B$7 -> 90 | I16: =$B$8 -> 11970 | J16: =G16-H16-I16 -> -11380.56 | K16: =J16-Inputs!B16 -> -11380.56 | L16: =MIN(J16:J51) -> -11380.56
A17: 2 | B17: =IF(Inputs!B22=0,1,1/(1+EXP(-Inputs!B22*(A17-Inputs!B21)))) -> 0.73105858 | C17: =IF(A17-Inputs!B23<1,0,$B$9*IF(Inputs!B22=0,1,1/(1+EXP(-Inputs!B22*(A17-Inputs!B23-Inputs!B21))))) -> 1.3159054 | D17: =D16*(1-$B$5)+IF(A17-Inputs!B17<1,0,OFFSET(C17,-Inputs!B17,0)*(1-$B$5)^Inputs!B17) -> 6.27 | E17: =IF(D17>0,F17/D17,0) -> 146.95455 | F17: =F16*(1-$B$5)*(1+$B$6)+IF(A17-Inputs!B17<1,0,OFFSET(C17,-Inputs!B17,0)*(1-$B$5)^Inputs!B17)*$B$3 -> 921.405 | G17: =F17*$B$4 -> 737.124 | H17: =$B$9*B17*$B$7 -> 131.59054 | I17: =$B$8 -> 11970 | J17: =G17-H17-I17 -> -11364.467 | K17: =K16+J17 -> -22745.027 | L17: =MIN(J17:J51) -> -11364.467
A18: 3 | B18: =IF(Inputs!B22=0,1,1/(1+EXP(-Inputs!B22*(A18-Inputs!B21)))) -> 0.88079708 | C18: =IF(A18-Inputs!B23<1,0,$B$9*IF(Inputs!B22=0,1,1/(1+EXP(-Inputs!B22*(A18-Inputs!B23-Inputs!B21))))) -> 1.5854347 | D18: =D17*(1-$B$5)+IF(A18-Inputs!B17<1,0,OFFSET(C18,-Inputs!B17,0)*(1-$B$5)^Inputs!B17) -> 7.2066102 | E18: =IF(D18>0,F18/D18,0) -> 144.70736 | F18: =F17*(1-$B$5)*(1+$B$6)+IF(A18-Inputs!B17<1,0,OFFSET(C18,-Inputs!B17,0)*(1-$B$5)^Inputs!B17)*$B$3 -> 1042.8495 | G18: =F18*$B$4 -> 834.27961 | H18: =$B$9*B18*$B$7 -> 158.54347 | I18: =$B$8 -> 11970 | J18: =G18-H18-I18 -> -11294.264 | K18: =K17+J18 -> -34039.29 | L18: =MIN(J18:J51) -> -11294.264
A19: 4 | B19: =IF(Inputs!B22=0,1,1/(1+EXP(-Inputs!B22*(A19-Inputs!B21)))) -> 0.95257413 | C19: =IF(A19-Inputs!B23<1,0,$B$9*IF(Inputs!B22=0,1,1/(1+EXP(-Inputs!B22*(A19-Inputs!B23-Inputs!B21))))) -> 1.7146334 | D19: =D18*(1-$B$5)+IF(A19-Inputs!B17<1,0,OFFSET(C19,-Inputs!B17,0)*(1-$B$5)^Inputs!B17) -> 8.3524427 | E19: =IF(D19>0,F19/D19,0) -> 142.77654 | F19: =F18*(1-$B$5)*(1+$B$6)+IF(A19-Inputs!B17<1,0,OFFSET(C19,-Inputs!B17,0)*(1-$B$5)^Inputs!B17)*$B$3 -> 1192.5329 | G19: =F19*$B$4 -> 954.0263 | H19: =$B$9*B19*$B$7 -> 171.46334 | I19: =$B$8 -> 11970 | J19: =G19-H19-I19 -> -11187.437 | K19: =K18+J19 -> -45226.727 | L19: =MIN(J19:J51) -> -11187.437
A20: 5 | B20: =IF(Inputs!B22=0,1,1/(1+EXP(-Inputs!B22*(A20-Inputs!B21)))) -> 0.98201379 | C20: =IF(A20-Inputs!B23<1,0,$B$9*IF(Inputs!B22=0,1,1/(1+EXP(-Inputs!B22*(A20-Inputs!B23-Inputs!B21))))) -> 1.7676248 | D20: =D19*(1-$B$5)+IF(A20-Inputs!B17<1,0,OFFSET(C20,-Inputs!B17,0)*(1-$B$5)^Inputs!B17) -> 9.5637223 | E20: =IF(D20>0,F20/D20,0) -> 141.28171 | F20: =F19*(1-$B$5)*(1+$B$6)+IF(A20-Inputs!B17<1,0,OFFSET(C20,-Inputs!B17,0)*(1-$B$5)^Inputs!B17)*$B$3 -> 1351.1791 | G20: =F20*$B$4 -> 1080.9433 | H20: =$B$9*B20*$B$7 -> 176.76248 | I20: =$B$8 -> 11970 | J20: =G20-H20-I20 -> -11065.819 | K20: =K19+J20 -> -56292.547 | L20: =MIN(J20:J51) -> -11065.819
A21: 6 | B21: =IF(Inputs!B22=0,1,1/(1+EXP(-Inputs!B22*(A21-Inputs!B21)))) -> 0.99330715 | C21: =IF(A21-Inputs!B23<1,0,$B$9*IF(Inputs!B22=0,1,1/(1+EXP(-Inputs!B22*(A21-Inputs!B23-Inputs!B21))))) -> 1.7879529 | D21: =D20*(1-$B$5)+IF(A21-Inputs!B17<1,0,OFFSET(C21,-Inputs!B17,0)*(1-$B$5)^Inputs!B17) -> 10.76478 | E21: =IF(D21>0,F21/D21,0) -> 140.14581 | F21: =F20*(1-$B$5)*(1+$B$6)+IF(A21-Inputs!B17<1,0,OFFSET(C21,-Inputs!B17,0)*(1-$B$5)^Inputs!B17)*$B$3 -> 1508.6388 | G21: =F21*$B$4 -> 1206.911 | H21: =$B$9*B21*$B$7 -> 178.79529 | I21: =$B$8 -> 11970 | J21: =G21-H21-I21 -> -10941.884 | K21: =K20+J21 -> -67234.431 | L21: =MIN(J21:J51) -> -10941.884
A22: 7 | B22: =IF(Inputs!B22=0,1,1/(1+EXP(-Inputs!B22*(A22-Inputs!B21)))) -> 0.99752738 | C22: =IF(A22-Inputs!B23<1,0,$B$9*IF(Inputs!B22=0,1,1/(1+EXP(-Inputs!B22*(A22-Inputs!B23-Inputs!B21))))) -> 1.7955493 | D22: =D21*(1-$B$5)+IF(A22-Inputs!B17<1,0,OFFSET(C22,-Inputs!B17,0)*(1-$B$5)^Inputs!B17) -> 11.925096 | E22: =IF(D22>0,F22/D22,0) -> 139.27043 | F22: =F21*(1-$B$5)*(1+$B$6)+IF(A22-Inputs!B17<1,0,OFFSET(C22,-Inputs!B17,0)*(1-$B$5)^Inputs!B17)*$B$3 -> 1660.8132 | G22: =F22*$B$4 -> 1328.6506 | H22: =$B$9*B22*$B$7 -> 179.55493 | I22: =$B$8 -> 11970 | J22: =G22-H22-I22 -> -10820.904 | K22: =K21+J22 -> -78055.335 | L22: =MIN(J22:J51) -> -10820.904
A23: 8 | B23: =IF(Inputs!B22=0,1,1/(1+EXP(-Inputs!B22*(A23-Inputs!B21)))) -> 0.99908895 | C23: =IF(A23-Inputs!B23<1,0,$B$9*IF(Inputs!B22=0,1,1/(1+EXP(-Inputs!B22*(A23-Inputs!B23-Inputs!B21))))) -> 1.7983601 | D23: =D22*(1-$B$5)+IF(A23-Inputs!B17<1,0,OFFSET(C23,-Inputs!B17,0)*(1-$B$5)^Inputs!B17) -> 13.034613 | E23: =IF(D23>0,F23/D23,0) -> 138.58071 | F23: =F22*(1-$B$5)*(1+$B$6)+IF(A23-Inputs!B17<1,0,OFFSET(C23,-Inputs!B17,0)*(1-$B$5)^Inputs!B17)*$B$3 -> 1806.346 | G23: =F23*$B$4 -> 1445.0768 | H23: =$B$9*B23*$B$7 -> 179.83601 | I23: =$B$8 -> 11970 | J23: =G23-H23-I23 -> -10704.759 | K23: =K22+J23 -> -88760.095 | L23: =MIN(J23:J51) -> -10704.759
A24: 9 | B24: =IF(Inputs!B22=0,1,1/(1+EXP(-Inputs!B22*(A24-Inputs!B21)))) -> 0.99966465 | C24: =IF(A24-Inputs!B23<1,0,$B$9*IF(Inputs!B22=0,1,1/(1+EXP(-Inputs!B22*(A24-Inputs!B23-Inputs!B21))))) -> 1.7993964 | D24: =D23*(1-$B$5)+IF(A24-Inputs!B17<1,0,OFFSET(C24,-Inputs!B17,0)*(1-$B$5)^Inputs!B17) -> 14.091324 | E24: =IF(D24>0,F24/D24,0) -> 138.02535 | F24: =F23*(1-$B$5)*(1+$B$6)+IF(A24-Inputs!B17<1,0,OFFSET(C24,-Inputs!B17,0)*(1-$B$5)^Inputs!B17)*$B$3 -> 1944.9599 | G24: =F24*$B$4 -> 1555.9679 | H24: =$B$9*B24*$B$7 -> 179.93964 | I24: =$B$8 -> 11970 | J24: =G24-H24-I24 -> -10593.972 | K24: =K23+J24 -> -99354.066 | L24: =MIN(J24:J51) -> -10593.972
A25: 10 | B25: =IF(Inputs!B22=0,1,1/(1+EXP(-Inputs!B22*(A25-Inputs!B21)))) -> 0.99987661 | C25: =IF(A25-Inputs!B23<1,0,$B$9*IF(Inputs!B22=0,1,1/(1+EXP(-Inputs!B22*(A25-Inputs!B23-Inputs!B21))))) -> 1.7997779 | D25: =D24*(1-$B$5)+IF(A25-Inputs!B17<1,0,OFFSET(C25,-Inputs!B17,0)*(1-$B$5)^Inputs!B17) -> 15.096185 | E25: =IF(D25>0,F25/D25,0) -> 137.56953 | F25: =F24*(1-$B$5)*(1+$B$6)+IF(A25-Inputs!B17<1,0,OFFSET(C25,-Inputs!B17,0)*(1-$B$5)^Inputs!B17)*$B$3 -> 2076.7751 | G25: =F25*$B$4 -> 1661.4201 | H25: =$B$9*B25*$B$7 -> 179.97779 | I25: =$B$8 -> 11970 | J25: =G25-H25-I25 -> -10488.558 | K25: =K24+J25 -> -109842.62 | L25: =MIN(J25:J51) -> -10488.558
A26: 11 | B26: =IF(Inputs!B22=0,1,1/(1+EXP(-Inputs!B22*(A26-Inputs!B21)))) -> 0.9999546 | C26: =IF(A26-Inputs!B23<1,0,$B$9*IF(Inputs!B22=0,1,1/(1+EXP(-Inputs!B22*(A26-Inputs!B23-Inputs!B21))))) -> 1.7999183 | D26: =D25*(1-$B$5)+IF(A26-Inputs!B17<1,0,OFFSET(C26,-Inputs!B17,0)*(1-$B$5)^Inputs!B17) -> 16.051165 | E26: =IF(D26>0,F26/D26,0) -> 137.1893 | F26: =F25*(1-$B$5)*(1+$B$6)+IF(A26-Inputs!B17<1,0,OFFSET(C26,-Inputs!B17,0)*(1-$B$5)^Inputs!B17)*$B$3 -> 2202.0481 | G26: =F26*$B$4 -> 1761.6384 | H26: =$B$9*B26*$B$7 -> 179.99183 | I26: =$B$8 -> 11970 | J26: =G26-H26-I26 -> -10388.353 | K26: =K25+J26 -> -120230.98 | L26: =MIN(J26:J51) -> -10388.353
A27: 12 | B27: =IF(Inputs!B22=0,1,1/(1+EXP(-Inputs!B22*(A27-Inputs!B21)))) -> 0.9999833 | C27: =IF(A27-Inputs!B23<1,0,$B$9*IF(Inputs!B22=0,1,1/(1+EXP(-Inputs!B22*(A27-Inputs!B23-Inputs!B21))))) -> 1.7999699 | D27: =D26*(1-$B$5)+IF(A27-Inputs!B17<1,0,OFFSET(C27,-Inputs!B17,0)*(1-$B$5)^Inputs!B17) -> 16.958529 | E27: =IF(D27>0,F27/D27,0) -> 136.86773 | F27: =F26*(1-$B$5)*(1+$B$6)+IF(A27-Inputs!B17<1,0,OFFSET(C27,-Inputs!B17,0)*(1-$B$5)^Inputs!B17)*$B$3 -> 2321.0753 | G27: =F27*$B$4 -> 1856.8602 | H27: =$B$9*B27*$B$7 -> 179.99699 | I27: =$B$8 -> 11970 | J27: =G27-H27-I27 -> -10293.137 | K27: =K26+J27 -> -130524.11 | L27: =MIN(J27:J51) -> -10293.137
A28: 13 | B28: =IF(Inputs!B22=0,1,1/(1+EXP(-Inputs!B22*(A28-Inputs!B21)))) -> 0.99999386 | C28: =IF(A28-Inputs!B23<1,0,$B$9*IF(Inputs!B22=0,1,1/(1+EXP(-Inputs!B22*(A28-Inputs!B23-Inputs!B21))))) -> 1.7999889 | D28: =D27*(1-$B$5)+IF(A28-Inputs!B17<1,0,OFFSET(C28,-Inputs!B17,0)*(1-$B$5)^Inputs!B17) -> 17.820574 | E28: =IF(D28>0,F28/D28,0) -> 136.59255 | F28: =F27*(1-$B$5)*(1+$B$6)+IF(A28-Inputs!B17<1,0,OFFSET(C28,-Inputs!B17,0)*(1-$B$5)^Inputs!B17)*$B$3 -> 2434.1577 | G28: =F28*$B$4 -> 1947.3261 | H28: =$B$9*B28*$B$7 -> 179.99889 | I28: =$B$8 -> 11970 | J28: =G28-H28-I28 -> -10202.673 | K28: =K27+J28 -> -140726.79 | L28: =MIN(J28:J51) -> -10202.673
A29: 14 | B29: =IF(Inputs!B22=0,1,1/(1+EXP(-Inputs!B22*(A29-Inputs!B21)))) -> 0.99999774 | C29: =IF(A29-Inputs!B23<1,0,$B$9*IF(Inputs!B22=0,1,1/(1+EXP(-Inputs!B22*(A29-Inputs!B23-Inputs!B21))))) -> 1.7999959 | D29: =D28*(1-$B$5)+IF(A29-Inputs!B17<1,0,OFFSET(C29,-Inputs!B17,0)*(1-$B$5)^Inputs!B17) -> 18.639535 | E29: =IF(D29>0,F29/D29,0) -> 136.35471 | F29: =F28*(1-$B$5)*(1+$B$6)+IF(A29-Inputs!B17<1,0,OFFSET(C29,-Inputs!B17,0)*(1-$B$5)^Inputs!B17)*$B$3 -> 2541.5884 | G29: =F29*$B$4 -> 2033.2707 | H29: =$B$9*B29*$B$7 -> 179.99959 | I29: =$B$8 -> 11970 | J29: =G29-H29-I29 -> -10116.729 | K29: =K28+J29 -> -150843.52 | L29: =MIN(J29:J51) -> -10116.729
A30: 15 | B30: =IF(Inputs!B22=0,1,1/(1+EXP(-Inputs!B22*(A30-Inputs!B21)))) -> 0.99999917 | C30: =IF(A30-Inputs!B23<1,0,$B$9*IF(Inputs!B22=0,1,1/(1+EXP(-Inputs!B22*(A30-Inputs!B23-Inputs!B21))))) -> 1.7999985 | D30: =D29*(1-$B$5)+IF(A30-Inputs!B17<1,0,OFFSET(C30,-Inputs!B17,0)*(1-$B$5)^Inputs!B17) -> 19.417554 | E30: =IF(D30>0,F30/D30,0) -> 136.14735 | F30: =F29*(1-$B$5)*(1+$B$6)+IF(A30-Inputs!B17<1,0,OFFSET(C30,-Inputs!B17,0)*(1-$B$5)^Inputs!B17)*$B$3 -> 2643.6484 | G30: =F30*$B$4 -> 2114.9187 | H30: =$B$9*B30*$B$7 -> 179.99985 | I30: =$B$8 -> 11970 | J30: =G30-H30-I30 -> -10035.081 | K30: =K29+J30 -> -160878.6 | L30: =MIN(J30:J51) -> -10035.081
A31: 16 | B31: =IF(Inputs!B22=0,1,1/(1+EXP(-Inputs!B22*(A31-Inputs!B21)))) -> 0.99999969 | C31: =IF(A31-Inputs!B23<1,0,$B$9*IF(Inputs!B22=0,1,1/(1+EXP(-Inputs!B22*(A31-Inputs!B23-Inputs!B21))))) -> 1.7999994 | D31: =D30*(1-$B$5)+IF(A31-Inputs!B17<1,0,OFFSET(C31,-Inputs!B17,0)*(1-$B$5)^Inputs!B17) -> 20.156675 | E31: =IF(D31>0,F31/D31,0) -> 135.96518 | F31: =F30*(1-$B$5)*(1+$B$6)+IF(A31-Inputs!B17<1,0,OFFSET(C31,-Inputs!B17,0)*(1-$B$5)^Inputs!B17)*$B$3 -> 2740.6058 | G31: =F31*$B$4 -> 2192.4847 | H31: =$B$9*B31*$B$7 -> 179.99994 | I31: =$B$8 -> 11970 | J31: =G31-H31-I31 -> -9957.5153 | K31: =K30+J31 -> -170836.11 | L31: =MIN(J31:J51) -> -9957.5153
A32: 17 | B32: =IF(Inputs!B22=0,1,1/(1+EXP(-Inputs!B22*(A32-Inputs!B21)))) -> 0.99999989 | C32: =IF(A32-Inputs!B23<1,0,$B$9*IF(Inputs!B22=0,1,1/(1+EXP(-Inputs!B22*(A32-Inputs!B23-Inputs!B21))))) -> 1.7999998 | D32: =D31*(1-$B$5)+IF(A32-Inputs!B17<1,0,OFFSET(C32,-Inputs!B17,0)*(1-$B$5)^Inputs!B17) -> 20.858841 | E32: =IF(D32>0,F32/D32,0) -> 135.80407 | F32: =F31*(1-$B$5)*(1+$B$6)+IF(A32-Inputs!B17<1,0,OFFSET(C32,-Inputs!B17,0)*(1-$B$5)^Inputs!B17)*$B$3 -> 2832.7155 | G32: =F32*$B$4 -> 2266.1724 | H32: =$B$9*B32*$B$7 -> 179.99998 | I32: =$B$8 -> 11970 | J32: =G32-H32-I32 -> -9883.8276 | K32: =K31+J32 -> -180719.94 | L32: =MIN(J32:J51) -> -9883.8276
A33: 18 | B33: =IF(Inputs!B22=0,1,1/(1+EXP(-Inputs!B22*(A33-Inputs!B21)))) -> 0.99999996 | C33: =IF(A33-Inputs!B23<1,0,$B$9*IF(Inputs!B22=0,1,1/(1+EXP(-Inputs!B22*(A33-Inputs!B23-Inputs!B21))))) -> 1.7999999 | D33: =D32*(1-$B$5)+IF(A33-Inputs!B17<1,0,OFFSET(C33,-Inputs!B17,0)*(1-$B$5)^Inputs!B17) -> 21.525898 | E33: =IF(D33>0,F33/D33,0) -> 135.66076 | F33: =F32*(1-$B$5)*(1+$B$6)+IF(A33-Inputs!B17<1,0,OFFSET(C33,-Inputs!B17,0)*(1-$B$5)^Inputs!B17)*$B$3 -> 2920.2197 | G33: =F33*$B$4 -> 2336.1757 | H33: =$B$9*B33*$B$7 -> 179.99999 | I33: =$B$8 -> 11970 | J33: =G33-H33-I33 -> -9813.8243 | K33: =K32+J33 -> -190533.76 | L33: =MIN(J33:J51) -> -9813.8243
A34: 19 | B34: =IF(Inputs!B22=0,1,1/(1+EXP(-Inputs!B22*(A34-Inputs!B21)))) -> 0.99999998 | C34: =IF(A34-Inputs!B23<1,0,$B$9*IF(Inputs!B22=0,1,1/(1+EXP(-Inputs!B22*(A34-Inputs!B23-Inputs!B21))))) -> 1.8 | D34: =D33*(1-$B$5)+IF(A34-Inputs!B17<1,0,OFFSET(C34,-Inputs!B17,0)*(1-$B$5)^Inputs!B17) -> 22.159603 | E34: =IF(D34>0,F34/D34,0) -> 135.5326 | F34: =F33*(1-$B$5)*(1+$B$6)+IF(A34-Inputs!B17<1,0,OFFSET(C34,-Inputs!B17,0)*(1-$B$5)^Inputs!B17)*$B$3 -> 3003.3487 | G34: =F34*$B$4 -> 2402.6789 | H34: =$B$9*B34*$B$7 -> 180 | I34: =$B$8 -> 11970 | J34: =G34-H34-I34 -> -9747.3211 | K34: =K33+J34 -> -200281.09 | L34: =MIN(J34:J51) -> -9747.3211
A35: 20 | B35: =IF(Inputs!B22=0,1,1/(1+EXP(-Inputs!B22*(A35-Inputs!B21)))) -> 0.99999999 | C35: =IF(A35-Inputs!B23<1,0,$B$9*IF(Inputs!B22=0,1,1/(1+EXP(-Inputs!B22*(A35-Inputs!B23-Inputs!B21))))) -> 1.8 | D35: =D34*(1-$B$5)+IF(A35-Inputs!B17<1,0,OFFSET(C35,-Inputs!B17,0)*(1-$B$5)^Inputs!B17) -> 22.761623 | E35: =IF(D35>0,F35/D35,0) -> 135.41746 | F35: =F34*(1-$B$5)*(1+$B$6)+IF(A35-Inputs!B17<1,0,OFFSET(C35,-Inputs!B17,0)*(1-$B$5)^Inputs!B17)*$B$3 -> 3082.3212 | G35: =F35*$B$4 -> 2465.857 | H35: =$B$9*B35*$B$7 -> 180 | I35: =$B$8 -> 11970 | J35: =G35-H35-I35 -> -9684.143 | K35: =K34+J35 -> -209965.23 | L35: =MIN(J35:J51) -> -9684.143
A36: 21 | B36: =IF(Inputs!B22=0,1,1/(1+EXP(-Inputs!B22*(A36-Inputs!B21)))) -> 1 | C36: =IF(A36-Inputs!B23<1,0,$B$9*IF(Inputs!B22=0,1,1/(1+EXP(-Inputs!B22*(A36-Inputs!B23-Inputs!B21))))) -> 1.8 | D36: =D35*(1-$B$5)+IF(A36-Inputs!B17<1,0,OFFSET(C36,-Inputs!B17,0)*(1-$B$5)^Inputs!B17) -> 23.333542 | E36: =IF(D36>0,F36/D36,0) -> 135.31358 | F36: =F35*(1-$B$5)*(1+$B$6)+IF(A36-Inputs!B17<1,0,OFFSET(C36,-Inputs!B17,0)*(1-$B$5)^Inputs!B17)*$B$3 -> 3157.3452 | G36: =F36*$B$4 -> 2525.8761 | H36: =$B$9*B36*$B$7 -> 180 | I36: =$B$8 -> 11970 | J36: =G36-H36-I36 -> -9624.1239 | K36: =K35+J36 -> -219589.35 | L36: =MIN(J36:J51) -> -9624.1239
A37: 22 | B37: =IF(Inputs!B22=0,1,1/(1+EXP(-Inputs!B22*(A37-Inputs!B21)))) -> 1 | C37: =IF(A37-Inputs!B23<1,0,$B$9*IF(Inputs!B22=0,1,1/(1+EXP(-Inputs!B22*(A37-Inputs!B23-Inputs!B21))))) -> 1.8 | D37: =D36*(1-$B$5)+IF(A37-Inputs!B17<1,0,OFFSET(C37,-Inputs!B17,0)*(1-$B$5)^Inputs!B17) -> 23.876865 | E37: =IF(D37>0,F37/D37,0) -> 135.21951 | F37: =F36*(1-$B$5)*(1+$B$6)+IF(A37-Inputs!B17<1,0,OFFSET(C37,-Inputs!B17,0)*(1-$B$5)^Inputs!B17)*$B$3 -> 3228.6179 | G37: =F37*$B$4 -> 2582.8943 | H37: =$B$9*B37*$B$7 -> 180 | I37: =$B$8 -> 11970 | J37: =G37-H37-I37 -> -9567.1057 | K37: =K36+J37 -> -229156.46 | L37: =MIN(J37:J51) -> -9567.1057
A38: 23 | B38: =IF(Inputs!B22=0,1,1/(1+EXP(-Inputs!B22*(A38-Inputs!B21)))) -> 1 | C38: =IF(A38-Inputs!B23<1,0,$B$9*IF(Inputs!B22=0,1,1/(1+EXP(-Inputs!B22*(A38-Inputs!B23-Inputs!B21))))) -> 1.8 | D38: =D37*(1-$B$5)+IF(A38-Inputs!B17<1,0,OFFSET(C38,-Inputs!B17,0)*(1-$B$5)^Inputs!B17) -> 24.393022 | E38: =IF(D38>0,F38/D38,0) -> 135.13402 | F38: =F37*(1-$B$5)*(1+$B$6)+IF(A38-Inputs!B17<1,0,OFFSET(C38,-Inputs!B17,0)*(1-$B$5)^Inputs!B17)*$B$3 -> 3296.327 | G38: =F38*$B$4 -> 2637.0616 | H38: =$B$9*B38*$B$7 -> 180 | I38: =$B$8 -> 11970 | J38: =G38-H38-I38 -> -9512.9384 | K38: =K37+J38 -> -238669.4 | L38: =MIN(J38:J51) -> -9512.9384
A39: 24 | B39: =IF(Inputs!B22=0,1,1/(1+EXP(-Inputs!B22*(A39-Inputs!B21)))) -> 1 | C39: =IF(A39-Inputs!B23<1,0,$B$9*IF(Inputs!B22=0,1,1/(1+EXP(-Inputs!B22*(A39-Inputs!B23-Inputs!B21))))) -> 1.8 | D39: =D38*(1-$B$5)+IF(A39-Inputs!B17<1,0,OFFSET(C39,-Inputs!B17,0)*(1-$B$5)^Inputs!B17) -> 24.883371 | E39: =IF(D39>0,F39/D39,0) -> 135.05609 | F39: =F38*(1-$B$5)*(1+$B$6)+IF(A39-Inputs!B17<1,0,OFFSET(C39,-Inputs!B17,0)*(1-$B$5)^Inputs!B17)*$B$3 -> 3360.6507 | G39: =F39*$B$4 -> 2688.5205 | H39: =$B$9*B39*$B$7 -> 180 | I39: =$B$8 -> 11970 | J39: =G39-H39-I39 -> -9461.4795 | K39: =K38+J39 -> -248130.88 | L39: =MIN(J39:J51) -> -9461.4795
A40: 25 | B40: =IF(Inputs!B22=0,1,1/(1+EXP(-Inputs!B22*(A40-Inputs!B21)))) -> 1 | C40: =IF(A40-Inputs!B23<1,0,$B$9*IF(Inputs!B22=0,1,1/(1+EXP(-Inputs!B22*(A40-Inputs!B23-Inputs!B21))))) -> 1.8 | D40: =D39*(1-$B$5)+IF(A40-Inputs!B17<1,0,OFFSET(C40,-Inputs!B17,0)*(1-$B$5)^Inputs!B17) -> 25.349202 | E40: =IF(D40>0,F40/D40,0) -> 134.98485 | F40: =F39*(1-$B$5)*(1+$B$6)+IF(A40-Inputs!B17<1,0,OFFSET(C40,-Inputs!B17,0)*(1-$B$5)^Inputs!B17)*$B$3 -> 3421.7581 | G40: =F40*$B$4 -> 2737.4065 | H40: =$B$9*B40*$B$7 -> 180 | I40: =$B$8 -> 11970 | J40: =G40-H40-I40 -> -9412.5935 | K40: =K39+J40 -> -257543.47 | L40: =MIN(J40:J51) -> -9412.5935
A41: 26 | B41: =IF(Inputs!B22=0,1,1/(1+EXP(-Inputs!B22*(A41-Inputs!B21)))) -> 1 | C41: =IF(A41-Inputs!B23<1,0,$B$9*IF(Inputs!B22=0,1,1/(1+EXP(-Inputs!B22*(A41-Inputs!B23-Inputs!B21))))) -> 1.8 | D41: =D40*(1-$B$5)+IF(A41-Inputs!B17<1,0,OFFSET(C41,-Inputs!B17,0)*(1-$B$5)^Inputs!B17) -> 25.791742 | E41: =IF(D41>0,F41/D41,0) -> 134.91955 | F41: =F40*(1-$B$5)*(1+$B$6)+IF(A41-Inputs!B17<1,0,OFFSET(C41,-Inputs!B17,0)*(1-$B$5)^Inputs!B17)*$B$3 -> 3479.8102 | G41: =F41*$B$4 -> 2783.8482 | H41: =$B$9*B41*$B$7 -> 180 | I41: =$B$8 -> 11970 | J41: =G41-H41-I41 -> -9366.1518 | K41: =K40+J41 -> -266909.62 | L41: =MIN(J41:J51) -> -9366.1518
A42: 27 | B42: =IF(Inputs!B22=0,1,1/(1+EXP(-Inputs!B22*(A42-Inputs!B21)))) -> 1 | C42: =IF(A42-Inputs!B23<1,0,$B$9*IF(Inputs!B22=0,1,1/(1+EXP(-Inputs!B22*(A42-Inputs!B23-Inputs!B21))))) -> 1.8 | D42: =D41*(1-$B$5)+IF(A42-Inputs!B17<1,0,OFFSET(C42,-Inputs!B17,0)*(1-$B$5)^Inputs!B17) -> 26.212155 | E42: =IF(D42>0,F42/D42,0) -> 134.85956 | F42: =F41*(1-$B$5)*(1+$B$6)+IF(A42-Inputs!B17<1,0,OFFSET(C42,-Inputs!B17,0)*(1-$B$5)^Inputs!B17)*$B$3 -> 3534.9597 | G42: =F42*$B$4 -> 2827.9678 | H42: =$B$9*B42*$B$7 -> 180 | I42: =$B$8 -> 11970 | J42: =G42-H42-I42 -> -9322.0322 | K42: =K41+J42 -> -276231.65 | L42: =MIN(J42:J51) -> -9322.0322
A43: 28 | B43: =IF(Inputs!B22=0,1,1/(1+EXP(-Inputs!B22*(A43-Inputs!B21)))) -> 1 | C43: =IF(A43-Inputs!B23<1,0,$B$9*IF(Inputs!B22=0,1,1/(1+EXP(-Inputs!B22*(A43-Inputs!B23-Inputs!B21))))) -> 1.8 | D43: =D42*(1-$B$5)+IF(A43-Inputs!B17<1,0,OFFSET(C43,-Inputs!B17,0)*(1-$B$5)^Inputs!B17) -> 26.611547 | E43: =IF(D43>0,F43/D43,0) -> 134.80433 | F43: =F42*(1-$B$5)*(1+$B$6)+IF(A43-Inputs!B17<1,0,OFFSET(C43,-Inputs!B17,0)*(1-$B$5)^Inputs!B17)*$B$3 -> 3587.3517 | G43: =F43*$B$4 -> 2869.8814 | H43: =$B$9*B43*$B$7 -> 180 | I43: =$B$8 -> 11970 | J43: =G43-H43-I43 -> -9280.1186 | K43: =K42+J43 -> -285511.77 | L43: =MIN(J43:J51) -> -9280.1186
A44: 29 | B44: =IF(Inputs!B22=0,1,1/(1+EXP(-Inputs!B22*(A44-Inputs!B21)))) -> 1 | C44: =IF(A44-Inputs!B23<1,0,$B$9*IF(Inputs!B22=0,1,1/(1+EXP(-Inputs!B22*(A44-Inputs!B23-Inputs!B21))))) -> 1.8 | D44: =D43*(1-$B$5)+IF(A44-Inputs!B17<1,0,OFFSET(C44,-Inputs!B17,0)*(1-$B$5)^Inputs!B17) -> 26.99097 | E44: =IF(D44>0,F44/D44,0) -> 134.75337 | F44: =F43*(1-$B$5)*(1+$B$6)+IF(A44-Inputs!B17<1,0,OFFSET(C44,-Inputs!B17,0)*(1-$B$5)^Inputs!B17)*$B$3 -> 3637.1241 | G44: =F44*$B$4 -> 2909.6993 | H44: =$B$9*B44*$B$7 -> 180 | I44: =$B$8 -> 11970 | J44: =G44-H44-I44 -> -9240.3007 | K44: =K43+J44 -> -294752.07 | L44: =MIN(J44:J51) -> -9240.3007
A45: 30 | B45: =IF(Inputs!B22=0,1,1/(1+EXP(-Inputs!B22*(A45-Inputs!B21)))) -> 1 | C45: =IF(A45-Inputs!B23<1,0,$B$9*IF(Inputs!B22=0,1,1/(1+EXP(-Inputs!B22*(A45-Inputs!B23-Inputs!B21))))) -> 1.8 | D45: =D44*(1-$B$5)+IF(A45-Inputs!B17<1,0,OFFSET(C45,-Inputs!B17,0)*(1-$B$5)^Inputs!B17) -> 27.351421 | E45: =IF(D45>0,F45/D45,0) -> 134.70627 | F45: =F44*(1-$B$5)*(1+$B$6)+IF(A45-Inputs!B17<1,0,OFFSET(C45,-Inputs!B17,0)*(1-$B$5)^Inputs!B17)*$B$3 -> 3684.4079 | G45: =F45*$B$4 -> 2947.5263 | H45: =$B$9*B45*$B$7 -> 180 | I45: =$B$8 -> 11970 | J45: =G45-H45-I45 -> -9202.4737 | K45: =K44+J45 -> -303954.55 | L45: =MIN(J45:J51) -> -9202.4737
A46: 31 | B46: =IF(Inputs!B22=0,1,1/(1+EXP(-Inputs!B22*(A46-Inputs!B21)))) -> 1 | C46: =IF(A46-Inputs!B23<1,0,$B$9*IF(Inputs!B22=0,1,1/(1+EXP(-Inputs!B22*(A46-Inputs!B23-Inputs!B21))))) -> 1.8 | D46: =D45*(1-$B$5)+IF(A46-Inputs!B17<1,0,OFFSET(C46,-Inputs!B17,0)*(1-$B$5)^Inputs!B17) -> 27.69385 | E46: =IF(D46>0,F46/D46,0) -> 134.66266 | F46: =F45*(1-$B$5)*(1+$B$6)+IF(A46-Inputs!B17<1,0,OFFSET(C46,-Inputs!B17,0)*(1-$B$5)^Inputs!B17)*$B$3 -> 3729.3275 | G46: =F46*$B$4 -> 2983.462 | H46: =$B$9*B46*$B$7 -> 180 | I46: =$B$8 -> 11970 | J46: =G46-H46-I46 -> -9166.538 | K46: =K45+J46 -> -313121.08 | L46: =MIN(J46:J51) -> -9166.538
A47: 32 | B47: =IF(Inputs!B22=0,1,1/(1+EXP(-Inputs!B22*(A47-Inputs!B21)))) -> 1 | C47: =IF(A47-Inputs!B23<1,0,$B$9*IF(Inputs!B22=0,1,1/(1+EXP(-Inputs!B22*(A47-Inputs!B23-Inputs!B21))))) -> 1.8 | D47: =D46*(1-$B$5)+IF(A47-Inputs!B17<1,0,OFFSET(C47,-Inputs!B17,0)*(1-$B$5)^Inputs!B17) -> 28.019158 | E47: =IF(D47>0,F47/D47,0) -> 134.62222 | F47: =F46*(1-$B$5)*(1+$B$6)+IF(A47-Inputs!B17<1,0,OFFSET(C47,-Inputs!B17,0)*(1-$B$5)^Inputs!B17)*$B$3 -> 3772.0012 | G47: =F47*$B$4 -> 3017.6009 | H47: =$B$9*B47*$B$7 -> 180 | I47: =$B$8 -> 11970 | J47: =G47-H47-I47 -> -9132.3991 | K47: =K46+J47 -> -322253.48 | L47: =MIN(J47:J51) -> -9132.3991
A48: 33 | B48: =IF(Inputs!B22=0,1,1/(1+EXP(-Inputs!B22*(A48-Inputs!B21)))) -> 1 | C48: =IF(A48-Inputs!B23<1,0,$B$9*IF(Inputs!B22=0,1,1/(1+EXP(-Inputs!B22*(A48-Inputs!B23-Inputs!B21))))) -> 1.8 | D48: =D47*(1-$B$5)+IF(A48-Inputs!B17<1,0,OFFSET(C48,-Inputs!B17,0)*(1-$B$5)^Inputs!B17) -> 28.3282 | E48: =IF(D48>0,F48/D48,0) -> 134.58466 | F48: =F47*(1-$B$5)*(1+$B$6)+IF(A48-Inputs!B17<1,0,OFFSET(C48,-Inputs!B17,0)*(1-$B$5)^Inputs!B17)*$B$3 -> 3812.5411 | G48: =F48*$B$4 -> 3050.0329 | H48: =$B$9*B48*$B$7 -> 180 | I48: =$B$8 -> 11970 | J48: =G48-H48-I48 -> -9099.9671 | K48: =K47+J48 -> -331353.45 | L48: =MIN(J48:J51) -> -9099.9671
A49: 34 | B49: =IF(Inputs!B22=0,1,1/(1+EXP(-Inputs!B22*(A49-Inputs!B21)))) -> 1 | C49: =IF(A49-Inputs!B23<1,0,$B$9*IF(Inputs!B22=0,1,1/(1+EXP(-Inputs!B22*(A49-Inputs!B23-Inputs!B21))))) -> 1.8 | D49: =D48*(1-$B$5)+IF(A49-Inputs!B17<1,0,OFFSET(C49,-Inputs!B17,0)*(1-$B$5)^Inputs!B17) -> 28.62179 | E49: =IF(D49>0,F49/D49,0) -> 134.54973 | F49: =F48*(1-$B$5)*(1+$B$6)+IF(A49-Inputs!B17<1,0,OFFSET(C49,-Inputs!B17,0)*(1-$B$5)^Inputs!B17)*$B$3 -> 3851.054 | G49: =F49*$B$4 -> 3080.8432 | H49: =$B$9*B49*$B$7 -> 180 | I49: =$B$8 -> 11970 | J49: =G49-H49-I49 -> -9069.1568 | K49: =K48+J49 -> -340422.61 | L49: =MIN(J49:J51) -> -9069.1568
A50: 35 | B50: =IF(Inputs!B22=0,1,1/(1+EXP(-Inputs!B22*(A50-Inputs!B21)))) -> 1 | C50: =IF(A50-Inputs!B23<1,0,$B$9*IF(Inputs!B22=0,1,1/(1+EXP(-Inputs!B22*(A50-Inputs!B23-Inputs!B21))))) -> 1.8 | D50: =D49*(1-$B$5)+IF(A50-Inputs!B17<1,0,OFFSET(C50,-Inputs!B17,0)*(1-$B$5)^Inputs!B17) -> 28.9007 | E50: =IF(D50>0,F50/D50,0) -> 134.5172 | F50: =F49*(1-$B$5)*(1+$B$6)+IF(A50-Inputs!B17<1,0,OFFSET(C50,-Inputs!B17,0)*(1-$B$5)^Inputs!B17)*$B$3 -> 3887.6413 | G50: =F50*$B$4 -> 3110.1131 | H50: =$B$9*B50*$B$7 -> 180 | I50: =$B$8 -> 11970 | J50: =G50-H50-I50 -> -9039.8869 | K50: =K49+J50 -> -349462.49 | L50: =MIN(J50:J51) -> -9039.8869
A51: 36 | B51: =IF(Inputs!B22=0,1,1/(1+EXP(-Inputs!B22*(A51-Inputs!B21)))) -> 1 | C51: =IF(A51-Inputs!B23<1,0,$B$9*IF(Inputs!B22=0,1,1/(1+EXP(-Inputs!B22*(A51-Inputs!B23-Inputs!B21))))) -> 1.8 | D51: =D50*(1-$B$5)+IF(A51-Inputs!B17<1,0,OFFSET(C51,-Inputs!B17,0)*(1-$B$5)^Inputs!B17) -> 29.165665 | E51: =IF(D51>0,F51/D51,0) -> 134.48688 | F51: =F50*(1-$B$5)*(1+$B$6)+IF(A51-Inputs!B17<1,0,OFFSET(C51,-Inputs!B17,0)*(1-$B$5)^Inputs!B17)*$B$3 -> 3922.3993 | G51: =F51*$B$4 -> 3137.9194 | H51: =$B$9*B51*$B$7 -> 180 | I51: =$B$8 -> 11970 | J51: =G51-H51-I51 -> -9012.0806 | K51: =K50+J51 -> -358474.57 | L51: =MIN(J51) -> -9012.0806
A53: Break-even month (net ≥ 0 from then on) | B53: =IFERROR(INDEX(A16:A51,MATCH(TRUE(),INDEX(L16:L51>=0,0),0)),"none") -> none
A54: Peak capital need | B54: =MAX(0,Inputs!B16,-MIN(K16:K51)) -> 358474.57
A55: Reference customers, 3y (segment × comparable penetration) | B55: =Inputs!B24*Inputs!C25 -> 75.36
A56: Bottom-up customers, month 36 (same 3-year window as the reference) | B56: =D51 -> 29.165665
A57: Ratio to reference | B57: =IF(B55>0,B56/B55,0) -> 0.38701785
A58: Position | B58: =IF(B57>1,"above_comparables",IF(B57<0.1,"far_below_comparables","within_range")) -> within_range

Sheet Pessimistic
A1: Pessimistic case
A3: Revenue per customer-month (ARPU₀) | B3: =Inputs!D5 -> 99
A4: Gross margin | B4: =Inputs!D6 -> 0.7
A5: Monthly churn | B5: =Inputs!E7 -> 0.07
A6: Monthly expansion | B6: =Inputs!D8 -> 0
A7: Blended CAC | B7: =Inputs!E11 -> 100
A8: Fixed burn / month | B8: =Inputs!B14*Inputs!E10+Inputs!B15 -> 16364
A9: New customers / month at full capacity | B9: =Inputs!D9 -> 1.2
A10: LTV (lifetime contribution, 60-mo cap) | B10: =B3*B4*(1-B5)^Inputs!B17*IF(ABS(1-(1-B5)*(1+B6))<0.000001,MAX(0,60-Inputs!B17),(1-((1-B5)*(1+B6))^MAX(0,60-Inputs!B17))/(1-(1-B5)*(1+B6))) -> 907.97634
A11: LTV / CAC (cash) | B11: =IF(B7>0,B10/B7,"n/a") -> 9.0797634
A12: Payback (months, cumulative; "none" = not within 60) | B12: =IF(B3*B4<=0,"none",IF(B7<=0,1+Inputs!B17,IF((1-B5)*(1+B6)<=0,IF(B7<=B3*B4*(1-B5)^Inputs!B17,1+Inputs!B17,"none"),IF(ABS(1-(1-B5)*(1+B6))<0.000001,IF(B7/(B3*B4*(1-B5)^Inputs!B17)<=60-Inputs!B17,ROUNDUP(B7/(B3*B4*(1-B5)^Inputs!B17),0)+Inputs!B17,"none"),IF(1-B7*(1-(1-B5)*(1+B6))/(B3*B4*(1-B5)^Inputs!B17)<=0,"none",IF(ROUNDUP(LN(1-B7*(1-(1-B5)*(1+B6))/(B3*B4*(1-B5)^Inputs!B17))/LN((1-B5)*(1+B6)),0)<=60-Inputs!B17,ROUNDUP(LN(1-B7*(1-(1-B5)*(1+B6))/(B3*B4*(1-B5)^Inputs!B17))/LN((1-B5)*(1+B6)),0)+Inputs!B17,"none")))))) -> 3
A15: Month | B15: Ramp | C15: New customers (arrivals) | D15: Paying customers | E15: ARPU (derived) | F15: Revenue | G15: Gross profit | H15: Acquisition spend | I15: Fixed burn | J15: Net cash flow | K15: Cumulative cash | L15: Lowest net from here on
A16: 1 | B16: =IF(Inputs!B22=0,1,1/(1+EXP(-Inputs!B22*(A16-Inputs!B21)))) -> 0.5 | C16: =IF(A16-Inputs!B23<1,0,$B$9*IF(Inputs!B22=0,1,1/(1+EXP(-Inputs!B22*(A16-Inputs!B23-Inputs!B21))))) -> 0.6 | D16: =Inputs!B19*(1-$B$5)+IF(A16-Inputs!B17<1,0,OFFSET(C16,-Inputs!B17,0)*(1-$B$5)^Inputs!B17) -> 5.58 | E16: =IF(D16>0,F16/D16,0) -> 149 | F16: =Inputs!B20*(1-$B$5)*(1+$B$6)+IF(A16-Inputs!B17<1,0,OFFSET(C16,-Inputs!B17,0)*(1-$B$5)^Inputs!B17)*$B$3 -> 831.42 | G16: =F16*$B$4 -> 581.994 | H16: =$B$9*B16*$B$7 -> 60 | I16: =$B$8 -> 16364 | J16: =G16-H16-I16 -> -15842.006 | K16: =J16-Inputs!B16 -> -15842.006 | L16: =MIN(J16:J51) -> -15873.827
A17: 2 | B17: =IF(Inputs!B22=0,1,1/(1+EXP(-Inputs!B22*(A17-Inputs!B21)))) -> 0.73105858 | C17: =IF(A17-Inputs!B23<1,0,$B$9*IF(Inputs!B22=0,1,1/(1+EXP(-Inputs!B22*(A17-Inputs!B23-Inputs!B21))))) -> 0.87727029 | D17: =D16*(1-$B$5)+IF(A17-Inputs!B17<1,0,OFFSET(C17,-Inputs!B17,0)*(1-$B$5)^Inputs!B17) -> 5.7474 | E17: =IF(D17>0,F17/D17,0) -> 144.14563 | F17: =F16*(1-$B$5)*(1+$B$6)+IF(A17-Inputs!B17<1,0,OFFSET(C17,-Inputs!B17,0)*(1-$B$5)^Inputs!B17)*$B$3 -> 828.4626 | G17: =F17*$B$4 -> 579.92382 | H17: =$B$9*B17*$B$7 -> 87.727029 | I17: =$B$8 -> 16364 | J17: =G17-H17-I17 -> -15871.803 | K17: =K16+J17 -> -31713.809 | L17: =MIN(J17:J51) -> -15873.827
A18: 3 | B18: =IF(Inputs!B22=0,1,1/(1+EXP(-Inputs!B22*(A18-Inputs!B21)))) -> 0.88079708 | C18: =IF(A18-Inputs!B23<1,0,$B$9*IF(Inputs!B22=0,1,1/(1+EXP(-Inputs!B22*(A18-Inputs!B23-Inputs!B21))))) -> 1.0569565 | D18: =D17*(1-$B$5)+IF(A18-Inputs!B17<1,0,OFFSET(C18,-Inputs!B17,0)*(1-$B$5)^Inputs!B17) -> 6.1609434 | E18: =IF(D18>0,F18/D18,0) -> 138.16723 | F18: =F17*(1-$B$5)*(1+$B$6)+IF(A18-Inputs!B17<1,0,OFFSET(C18,-Inputs!B17,0)*(1-$B$5)^Inputs!B17)*$B$3 -> 851.24049 | G18: =F18*$B$4 -> 595.86835 | H18: =$B$9*B18*$B$7 -> 105.69565 | I18: =$B$8 -> 16364 | J18: =G18-H18-I18 -> -15873.827 | K18: =K17+J18 -> -47587.637 | L18: =MIN(J18:J51) -> -15873.827
A19: 4 | B19: =IF(Inputs!B22=0,1,1/(1+EXP(-Inputs!B22*(A19-Inputs!B21)))) -> 0.95257413 | C19: =IF(A19-Inputs!B23<1,0,$B$9*IF(Inputs!B22=0,1,1/(1+EXP(-Inputs!B22*(A19-Inputs!B23-Inputs!B21))))) -> 1.143089 | D19: =D18*(1-$B$5)+IF(A19-Inputs!B17<1,0,OFFSET(C19,-Inputs!B17,0)*(1-$B$5)^Inputs!B17) -> 6.7126469 | E19: =IF(D19>0,F19/D19,0) -> 132.43176 | F19: =F18*(1-$B$5)*(1+$B$6)+IF(A19-Inputs!B17<1,0,OFFSET(C19,-Inputs!B17,0)*(1-$B$5)^Inputs!B17)*$B$3 -> 888.96764 | G19: =F19*$B$4 -> 622.27735 | H19: =$B$9*B19*$B$7 -> 114.3089 | I19: =$B$8 -> 16364 | J19: =G19-H19-I19 -> -15856.032 | K19: =K18+J19 -> -63443.668 | L19: =MIN(J19:J51) -> -15856.032
A20: 5 | B20: =IF(Inputs!B22=0,1,1/(1+EXP(-Inputs!B22*(A20-Inputs!B21)))) -> 0.98201379 | C20: =IF(A20-Inputs!B23<1,0,$B$9*IF(Inputs!B22=0,1,1/(1+EXP(-Inputs!B22*(A20-Inputs!B23-Inputs!B21))))) -> 1.1784165 | D20: =D19*(1-$B$5)+IF(A20-Inputs!B17<1,0,OFFSET(C20,-Inputs!B17,0)*(1-$B$5)^Inputs!B17) -> 7.3058343 | E20: =IF(D20>0,F20/D20,0) -> 127.5671 | F20: =F19*(1-$B$5)*(1+$B$6)+IF(A20-Inputs!B17<1,0,OFFSET(C20,-Inputs!B17,0)*(1-$B$5)^Inputs!B17)*$B$3 -> 931.98411 | G20: =F20*$B$4 -> 652.38888 | H20: =$B$9*B20*$B$7 -> 117.84165 | I20: =$B$8 -> 16364 | J20: =G20-H20-I20 -> -15829.453 | K20: =K19+J20 -> -79273.121 | L20: =MIN(J20:J51) -> -15829.453
A21: 6 | B21: =IF(Inputs!B22=0,1,1/(1+EXP(-Inputs!B22*(A21-Inputs!B21)))) -> 0.99330715 | C21: =IF(A21-Inputs!B23<1,0,$B$9*IF(Inputs!B22=0,1,1/(1+EXP(-Inputs!B22*(A21-Inputs!B23-Inputs!B21))))) -> 1.1919686 | D21: =D20*(1-$B$5)+IF(A21-Inputs!B17<1,0,OFFSET(C21,-Inputs!B17,0)*(1-$B$5)^Inputs!B17) -> 7.8903533 | E21: =IF(D21>0,F21/D21,0) -> 123.59929 | F21: =F20*(1-$B$5)*(1+$B$6)+IF(A21-Inputs!B17<1,0,OFFSET(C21,-Inputs!B17,0)*(1-$B$5)^Inputs!B17)*$B$3 -> 975.24203 | G21: =F21*$B$4 -> 682.66942 | H21: =$B$9*B21*$B$7 -> 119.19686 | I21: =$B$8 -> 16364 | J21: =G21-H21-I21 -> -15800.527 | K21: =K20+J21 -> -95073.648 | L21: =MIN(J21:J51) -> -15800.527
A22: 7 | B22: =IF(Inputs!B22=0,1,1/(1+EXP(-Inputs!B22*(A22-Inputs!B21)))) -> 0.99752738 | C22: =IF(A22-Inputs!B23<1,0,$B$9*IF(Inputs!B22=0,1,1/(1+EXP(-Inputs!B22*(A22-Inputs!B23-Inputs!B21))))) -> 1.1970329 | D22: =D21*(1-$B$5)+IF(A22-Inputs!B17<1,0,OFFSET(C22,-Inputs!B17,0)*(1-$B$5)^Inputs!B17) -> 8.4465594 | E22: =IF(D22>0,F22/D22,0) -> 120.37086 | F22: =F21*(1-$B$5)*(1+$B$6)+IF(A22-Inputs!B17<1,0,OFFSET(C22,-Inputs!B17,0)*(1-$B$5)^Inputs!B17)*$B$3 -> 1016.7196 | G22: =F22*$B$4 -> 711.70375 | H22: =$B$9*B22*$B$7 -> 119.70329 | I22: =$B$8 -> 16364 | J22: =G22-H22-I22 -> -15772 | K22: =K21+J22 -> -110845.65 | L22: =MIN(J22:J51) -> -15772
A23: 8 | B23: =IF(Inputs!B22=0,1,1/(1+EXP(-Inputs!B22*(A23-Inputs!B21)))) -> 0.99908895 | C23: =IF(A23-Inputs!B23<1,0,$B$9*IF(Inputs!B22=0,1,1/(1+EXP(-Inputs!B22*(A23-Inputs!B23-Inputs!B21))))) -> 1.1989067 | D23: =D22*(1-$B$5)+IF(A23-Inputs!B17<1,0,OFFSET(C23,-Inputs!B17,0)*(1-$B$5)^Inputs!B17) -> 8.9685408 | E23: =IF(D23>0,F23/D23,0) -> 117.71816 | F23: =F22*(1-$B$5)*(1+$B$6)+IF(A23-Inputs!B17<1,0,OFFSET(C23,-Inputs!B17,0)*(1-$B$5)^Inputs!B17)*$B$3 -> 1055.7601 | G23: =F23*$B$4 -> 739.03205 | H23: =$B$9*B23*$B$7 -> 119.89067 | I23: =$B$8 -> 16364 | J23: =G23-H23-I23 -> -15744.859 | K23: =K22+J23 -> -126590.51 | L23: =MIN(J23:J51) -> -15744.859
A24: 9 | B24: =IF(Inputs!B22=0,1,1/(1+EXP(-Inputs!B22*(A24-Inputs!B21)))) -> 0.99966465 | C24: =IF(A24-Inputs!B23<1,0,$B$9*IF(Inputs!B22=0,1,1/(1+EXP(-Inputs!B22*(A24-Inputs!B23-Inputs!B21))))) -> 1.1995976 | D24: =D23*(1-$B$5)+IF(A24-Inputs!B17<1,0,OFFSET(C24,-Inputs!B17,0)*(1-$B$5)^Inputs!B17) -> 9.4557262 | E24: =IF(D24>0,F24/D24,0) -> 115.51098 | F24: =F23*(1-$B$5)*(1+$B$6)+IF(A24-Inputs!B17<1,0,OFFSET(C24,-Inputs!B17,0)*(1-$B$5)^Inputs!B17)*$B$3 -> 1092.2402 | G24: =F24*$B$4 -> 764.56815 | H24: =$B$9*B24*$B$7 -> 119.95976 | I24: =$B$8 -> 16364 | J24: =G24-H24-I24 -> -15719.392 | K24: =K23+J24 -> -142309.9 | L24: =MIN(J24:J51) -> -15719.392
A25: 10 | B25: =IF(Inputs!B22=0,1,1/(1+EXP(-Inputs!B22*(A25-Inputs!B21)))) -> 0.99987661 | C25: =IF(A25-Inputs!B23<1,0,$B$9*IF(Inputs!B22=0,1,1/(1+EXP(-Inputs!B22*(A25-Inputs!B23-Inputs!B21))))) -> 1.1998519 | D25: =D24*(1-$B$5)+IF(A25-Inputs!B17<1,0,OFFSET(C25,-Inputs!B17,0)*(1-$B$5)^Inputs!B17) -> 9.9094511 | E25: =IF(D25>0,F25/D25,0) -> 113.65214 | F25: =F24*(1-$B$5)*(1+$B$6)+IF(A25-Inputs!B17<1,0,OFFSET(C25,-Inputs!B17,0)*(1-$B$5)^Inputs!B17)*$B$3 -> 1126.2303 | G25: =F25*$B$4 -> 788.36124 | H25: =$B$9*B25*$B$7 -> 119.98519 | I25: =$B$8 -> 16364 | J25: =G25-H25-I25 -> -15695.624 | K25: =K24+J25 -> -158005.52 | L25: =MIN(J25:J51) -> -15695.624
A26: 11 | B26: =IF(Inputs!B22=0,1,1/(1+EXP(-Inputs!B22*(A26-Inputs!B21)))) -> 0.9999546 | C26: =IF(A26-Inputs!B23<1,0,$B$9*IF(Inputs!B22=0,1,1/(1+EXP(-Inputs!B22*(A26-Inputs!B23-Inputs!B21))))) -> 1.1999455 | D26: =D25*(1-$B$5)+IF(A26-Inputs!B17<1,0,OFFSET(C26,-Inputs!B17,0)*(1-$B$5)^Inputs!B17) -> 10.331652 | E26: =IF(D26>0,F26/D26,0) -> 112.06965 | F26: =F25*(1-$B$5)*(1+$B$6)+IF(A26-Inputs!B17<1,0,OFFSET(C26,-Inputs!B17,0)*(1-$B$5)^Inputs!B17)*$B$3 -> 1157.8646 | G26: =F26*$B$4 -> 810.50521 | H26: =$B$9*B26*$B$7 -> 119.99455 | I26: =$B$8 -> 16364 | J26: =G26-H26-I26 -> -15673.489 | K26: =K25+J26 -> -173679.01 | L26: =MIN(J26:J51) -> -15673.489
A27: 12 | B27: =IF(Inputs!B22=0,1,1/(1+EXP(-Inputs!B22*(A27-Inputs!B21)))) -> 0.9999833 | C27: =IF(A27-Inputs!B23<1,0,$B$9*IF(Inputs!B22=0,1,1/(1+EXP(-Inputs!B22*(A27-Inputs!B23-Inputs!B21))))) -> 1.19998 | D27: =D26*(1-$B$5)+IF(A27-Inputs!B17<1,0,OFFSET(C27,-Inputs!B17,0)*(1-$B$5)^Inputs!B17) -> 10.724386 | E27: =IF(D27>0,F27/D27,0) -> 110.70966 | F27: =F26*(1-$B$5)*(1+$B$6)+IF(A27-Inputs!B17<1,0,OFFSET(C27,-Inputs!B17,0)*(1-$B$5)^Inputs!B17)*$B$3 -> 1187.2931 | G27: =F27*$B$4 -> 831.10514 | H27: =$B$9*B27*$B$7 -> 119.998 | I27: =$B$8 -> 16364 | J27: =G27-H27-I27 -> -15652.893 | K27: =K26+J27 -> -189331.9 | L27: =MIN(J27:J51) -> -15652.893
A28: 13 | B28: =IF(Inputs!B22=0,1,1/(1+EXP(-Inputs!B22*(A28-Inputs!B21)))) -> 0.99999386 | C28: =IF(A28-Inputs!B23<1,0,$B$9*IF(Inputs!B22=0,1,1/(1+EXP(-Inputs!B22*(A28-Inputs!B23-Inputs!B21))))) -> 1.1999926 | D28: =D27*(1-$B$5)+IF(A28-Inputs!B17<1,0,OFFSET(C28,-Inputs!B17,0)*(1-$B$5)^Inputs!B17) -> 11.08966 | E28: =IF(D28>0,F28/D28,0) -> 109.53128 | F28: =F27*(1-$B$5)*(1+$B$6)+IF(A28-Inputs!B17<1,0,OFFSET(C28,-Inputs!B17,0)*(1-$B$5)^Inputs!B17)*$B$3 -> 1214.6647 | G28: =F28*$B$4 -> 850.26529 | H28: =$B$9*B28*$B$7 -> 119.99926 | I28: =$B$8 -> 16364 | J28: =G28-H28-I28 -> -15633.734 | K28: =K27+J28 -> -204965.64 | L28: =MIN(J28:J51) -> -15633.734
A29: 14 | B29: =IF(Inputs!B22=0,1,1/(1+EXP(-Inputs!B22*(A29-Inputs!B21)))) -> 0.99999774 | C29: =IF(A29-Inputs!B23<1,0,$B$9*IF(Inputs!B22=0,1,1/(1+EXP(-Inputs!B22*(A29-Inputs!B23-Inputs!B21))))) -> 1.1999973 | D29: =D28*(1-$B$5)+IF(A29-Inputs!B17<1,0,OFFSET(C29,-Inputs!B17,0)*(1-$B$5)^Inputs!B17) -> 11.429377 | E29: =IF(D29>0,F29/D29,0) -> 108.50298 | F29: =F28*(1-$B$5)*(1+$B$6)+IF(A29-Inputs!B17<1,0,OFFSET(C29,-Inputs!B17,0)*(1-$B$5)^Inputs!B17)*$B$3 -> 1240.1215 | G29: =F29*$B$4 -> 868.08504 | H29: =$B$9*B29*$B$7 -> 119.99973 | I29: =$B$8 -> 16364 | J29: =G29-H29-I29 -> -15615.915 | K29: =K28+J29 -> -220581.55 | L29: =MIN(J29:J51) -> -15615.915
A30: 15 | B30: =IF(Inputs!B22=0,1,1/(1+EXP(-Inputs!B22*(A30-Inputs!B21)))) -> 0.99999917 | C30: =IF(A30-Inputs!B23<1,0,$B$9*IF(Inputs!B22=0,1,1/(1+EXP(-Inputs!B22*(A30-Inputs!B23-Inputs!B21))))) -> 1.199999 | D30: =D29*(1-$B$5)+IF(A30-Inputs!B17<1,0,OFFSET(C30,-Inputs!B17,0)*(1-$B$5)^Inputs!B17) -> 11.745318 | E30: =IF(D30>0,F30/D30,0) -> 107.60004 | F30: =F29*(1-$B$5)*(1+$B$6)+IF(A30-Inputs!B17<1,0,OFFSET(C30,-Inputs!B17,0)*(1-$B$5)^Inputs!B17)*$B$3 -> 1263.7967 | G30: =F30*$B$4 -> 884.65771 | H30: =$B$9*B30*$B$7 -> 119.9999 | I30: =$B$8 -> 16364 | J30: =G30-H30-I30 -> -15599.342 | K30: =K29+J30 -> -236180.9 | L30: =MIN(J30:J51) -> -15599.342
A31: 16 | B31: =IF(Inputs!B22=0,1,1/(1+EXP(-Inputs!B22*(A31-Inputs!B21)))) -> 0.99999969 | C31: =IF(A31-Inputs!B23<1,0,$B$9*IF(Inputs!B22=0,1,1/(1+EXP(-Inputs!B22*(A31-Inputs!B23-Inputs!B21))))) -> 1.1999996 | D31: =D30*(1-$B$5)+IF(A31-Inputs!B17<1,0,OFFSET(C31,-Inputs!B17,0)*(1-$B$5)^Inputs!B17) -> 12.039145 | E31: =IF(D31>0,F31/D31,0) -> 106.80284 | F31: =F30*(1-$B$5)*(1+$B$6)+IF(A31-Inputs!B17<1,0,OFFSET(C31,-Inputs!B17,0)*(1-$B$5)^Inputs!B17)*$B$3 -> 1285.8149 | G31: =F31*$B$4 -> 900.07041 | H31: =$B$9*B31*$B$7 -> 119.99996 | I31: =$B$8 -> 16364 | J31: =G31-H31-I31 -> -15583.93 | K31: =K30+J31 -> -251764.82 | L31: =MIN(J31:J51) -> -15583.93
A32: 17 | B32: =IF(Inputs!B22=0,1,1/(1+EXP(-Inputs!B22*(A32-Inputs!B21)))) -> 0.99999989 | C32: =IF(A32-Inputs!B23<1,0,$B$9*IF(Inputs!B22=0,1,1/(1+EXP(-Inputs!B22*(A32-Inputs!B23-Inputs!B21))))) -> 1.1999999 | D32: =D31*(1-$B$5)+IF(A32-Inputs!B17<1,0,OFFSET(C32,-Inputs!B17,0)*(1-$B$5)^Inputs!B17) -> 12.312404 | E32: =IF(D32>0,F32/D32,0) -> 106.09559 | F32: =F31*(1-$B$5)*(1+$B$6)+IF(A32-Inputs!B17<1,0,OFFSET(C32,-Inputs!B17,0)*(1-$B$5)^Inputs!B17)*$B$3 -> 1306.2918 | G32: =F32*$B$4 -> 914.40426 | H32: =$B$9*B32*$B$7 -> 119.99999 | I32: =$B$8 -> 16364 | J32: =G32-H32-I32 -> -15569.596 | K32: =K31+J32 -> -267334.42 | L32: =MIN(J32:J51) -> -15569.596
A33: 18 | B33: =IF(Inputs!B22=0,1,1/(1+EXP(-Inputs!B22*(A33-Inputs!B21)))) -> 0.99999996 | C33: =IF(A33-Inputs!B23<1,0,$B$9*IF(Inputs!B22=0,1,1/(1+EXP(-Inputs!B22*(A33-Inputs!B23-Inputs!B21))))) -> 1.2 | D33: =D32*(1-$B$5)+IF(A33-Inputs!B17<1,0,OFFSET(C33,-Inputs!B17,0)*(1-$B$5)^Inputs!B17) -> 12.566536 | E33: =IF(D33>0,F33/D33,0) -> 105.46545 | F33: =F32*(1-$B$5)*(1+$B$6)+IF(A33-Inputs!B17<1,0,OFFSET(C33,-Inputs!B17,0)*(1-$B$5)^Inputs!B17)*$B$3 -> 1325.3354 | G33: =F33*$B$4 -> 927.73475 | H33: =$B$9*B33*$B$7 -> 120 | I33: =$B$8 -> 16364 | J33: =G33-H33-I33 -> -15556.265 | K33: =K32+J33 -> -282890.69 | L33: =MIN(J33:J51) -> -15556.265
A34: 19 | B34: =IF(Inputs!B22=0,1,1/(1+EXP(-Inputs!B22*(A34-Inputs!B21)))) -> 0.99999998 | C34: =IF(A34-Inputs!B23<1,0,$B$9*IF(Inputs!B22=0,1,1/(1+EXP(-Inputs!B22*(A34-Inputs!B23-Inputs!B21))))) -> 1.2 | D34: =D33*(1-$B$5)+IF(A34-Inputs!B17<1,0,OFFSET(C34,-Inputs!B17,0)*(1-$B$5)^Inputs!B17) -> 12.802878 | E34: =IF(D34>0,F34/D34,0) -> 104.90187 | F34: =F33*(1-$B$5)*(1+$B$6)+IF(A34-Inputs!B17<1,0,OFFSET(C34,-Inputs!B17,0)*(1-$B$5)^Inputs!B17)*$B$3 -> 1343.0459 | G34: =F34*$B$4 -> 940.13211 | H34: =$B$9*B34*$B$7 -> 120 | I34: =$B$8 -> 16364 | J34: =G34-H34-I34 -> -15543.868 | K34: =K33+J34 -> -298434.55 | L34: =MIN(J34:J51) -> -15543.868
A35: 20 | B35: =IF(Inputs!B22=0,1,1/(1+EXP(-Inputs!B22*(A35-Inputs!B21)))) -> 0.99999999 | C35: =IF(A35-Inputs!B23<1,0,$B$9*IF(Inputs!B22=0,1,1/(1+EXP(-Inputs!B22*(A35-Inputs!B23-Inputs!B21))))) -> 1.2 | D35: =D34*(1-$B$5)+IF(A35-Inputs!B17<1,0,OFFSET(C35,-Inputs!B17,0)*(1-$B$5)^Inputs!B17) -> 13.022677 | E35: =IF(D35>0,F35/D35,0) -> 104.3961 | F35: =F34*(1-$B$5)*(1+$B$6)+IF(A35-Inputs!B17<1,0,OFFSET(C35,-Inputs!B17,0)*(1-$B$5)^Inputs!B17)*$B$3 -> 1359.5167 | G35: =F35*$B$4 -> 951.66167 | H35: =$B$9*B35*$B$7 -> 120 | I35: =$B$8 -> 16364 | J35: =G35-H35-I35 -> -15532.338 | K35: =K34+J35 -> -313966.89 | L35: =MIN(J35:J51) -> -15532.338
A36: 21 | B36: =IF(Inputs!B22=0,1,1/(1+EXP(-Inputs!B22*(A36-Inputs!B21)))) -> 1 | C36: =IF(A36-Inputs!B23<1,0,$B$9*IF(Inputs!B22=0,1,1/(1+EXP(-Inputs!B22*(A36-Inputs!B23-Inputs!B21))))) -> 1.2 | D36: =D35*(1-$B$5)+IF(A36-Inputs!B17<1,0,OFFSET(C36,-Inputs!B17,0)*(1-$B$5)^Inputs!B17) -> 13.227089 | E36: =IF(D36>0,F36/D36,0) -> 103.94082 | F36: =F35*(1-$B$5)*(1+$B$6)+IF(A36-Inputs!B17<1,0,OFFSET(C36,-Inputs!B17,0)*(1-$B$5)^Inputs!B17)*$B$3 -> 1374.8345 | G36: =F36*$B$4 -> 962.38415 | H36: =$B$9*B36*$B$7 -> 120 | I36: =$B$8 -> 16364 | J36: =G36-H36-I36 -> -15521.616 | K36: =K35+J36 -> -329488.51 | L36: =MIN(J36:J51) -> -15521.616
A37: 22 | B37: =IF(Inputs!B22=0,1,1/(1+EXP(-Inputs!B22*(A37-Inputs!B21)))) -> 1 | C37: =IF(A37-Inputs!B23<1,0,$B$9*IF(Inputs!B22=0,1,1/(1+EXP(-Inputs!B22*(A37-Inputs!B23-Inputs!B21))))) -> 1.2 | D37: =D36*(1-$B$5)+IF(A37-Inputs!B17<1,0,OFFSET(C37,-Inputs!B17,0)*(1-$B$5)^Inputs!B17) -> 13.417193 | E37: =IF(D37>0,F37/D37,0) -> 103.52986 | F37: =F36*(1-$B$5)*(1+$B$6)+IF(A37-Inputs!B17<1,0,OFFSET(C37,-Inputs!B17,0)*(1-$B$5)^Inputs!B17)*$B$3 -> 1389.0801 | G37: =F37*$B$4 -> 972.35606 | H37: =$B$9*B37*$B$7 -> 120 | I37: =$B$8 -> 16364 | J37: =G37-H37-I37 -> -15511.644 | K37: =K36+J37 -> -345000.15 | L37: =MIN(J37:J51) -> -15511.644
A38: 23 | B38: =IF(Inputs!B22=0,1,1/(1+EXP(-Inputs!B22*(A38-Inputs!B21)))) -> 1 | C38: =IF(A38-Inputs!B23<1,0,$B$9*IF(Inputs!B22=0,1,1/(1+EXP(-Inputs!B22*(A38-Inputs!B23-Inputs!B21))))) -> 1.2 | D38: =D37*(1-$B$5)+IF(A38-Inputs!B17<1,0,OFFSET(C38,-Inputs!B17,0)*(1-$B$5)^Inputs!B17) -> 13.59399 | E38: =IF(D38>0,F38/D38,0) -> 103.15798 | F38: =F37*(1-$B$5)*(1+$B$6)+IF(A38-Inputs!B17<1,0,OFFSET(C38,-Inputs!B17,0)*(1-$B$5)^Inputs!B17)*$B$3 -> 1402.3285 | G38: =F38*$B$4 -> 981.62993 | H38: =$B$9*B38*$B$7 -> 120 | I38: =$B$8 -> 16364 | J38: =G38-H38-I38 -> -15502.37 | K38: =K37+J38 -> -360502.52 | L38: =MIN(J38:J51) -> -15502.37
A39: 24 | B39: =IF(Inputs!B22=0,1,1/(1+EXP(-Inputs!B22*(A39-Inputs!B21)))) -> 1 | C39: =IF(A39-Inputs!B23<1,0,$B$9*IF(Inputs!B22=0,1,1/(1+EXP(-Inputs!B22*(A39-Inputs!B23-Inputs!B21))))) -> 1.2 | D39: =D38*(1-$B$5)+IF(A39-Inputs!B17<1,0,OFFSET(C39,-Inputs!B17,0)*(1-$B$5)^Inputs!B17) -> 13.75841 | E39: =IF(D39>0,F39/D39,0) -> 102.82071 | F39: =F38*(1-$B$5)*(1+$B$6)+IF(A39-Inputs!B17<1,0,OFFSET(C39,-Inputs!B17,0)*(1-$B$5)^Inputs!B17)*$B$3 -> 1414.6495 | G39: =F39*$B$4 -> 990.25464 | H39: =$B$9*B39*$B$7 -> 120 | I39: =$B$8 -> 16364 | J39: =G39-H39-I39 -> -15493.745 | K39: =K38+J39 -> -375996.27 | L39: =MIN(J39:J51) -> -15493.745
A40: 25 | B40: =IF(Inputs!B22=0,1,1/(1+EXP(-Inputs!B22*(A40-Inputs!B21)))) -> 1 | C40: =IF(A40-Inputs!B23<1,0,$B$9*IF(Inputs!B22=0,1,1/(1+EXP(-Inputs!B22*(A40-Inputs!B23-Inputs!B21))))) -> 1.2 | D40: =D39*(1-$B$5)+IF(A40-Inputs!B17<1,0,OFFSET(C40,-Inputs!B17,0)*(1-$B$5)^Inputs!B17) -> 13.911322 | E40: =IF(D40>0,F40/D40,0) -> 102.5142 | F40: =F39*(1-$B$5)*(1+$B$6)+IF(A40-Inputs!B17<1,0,OFFSET(C40,-Inputs!B17,0)*(1-$B$5)^Inputs!B17)*$B$3 -> 1426.108 | G40: =F40*$B$4 -> 998.27561 | H40: =$B$9*B40*$B$7 -> 120 | I40: =$B$8 -> 16364 | J40: =G40-H40-I40 -> -15485.724 | K40: =K39+J40 -> -391481.99 | L40: =MIN(J40:J51) -> -15485.724
A41: 26 | B41: =IF(Inputs!B22=0,1,1/(1+EXP(-Inputs!B22*(A41-Inputs!B21)))) -> 1 | C41: =IF(A41-Inputs!B23<1,0,$B$9*IF(Inputs!B22=0,1,1/(1+EXP(-Inputs!B22*(A41-Inputs!B23-Inputs!B21))))) -> 1.2 | D41: =D40*(1-$B$5)+IF(A41-Inputs!B17<1,0,OFFSET(C41,-Inputs!B17,0)*(1-$B$5)^Inputs!B17) -> 14.053529 | E41: =IF(D41>0,F41/D41,0) -> 102.23514 | F41: =F40*(1-$B$5)*(1+$B$6)+IF(A41-Inputs!B17<1,0,OFFSET(C41,-Inputs!B17,0)*(1-$B$5)^Inputs!B17)*$B$3 -> 1436.7645 | G41: =F41*$B$4 -> 1005.7351 | H41: =$B$9*B41*$B$7 -> 120 | I41: =$B$8 -> 16364 | J41: =G41-H41-I41 -> -15478.265 | K41: =K40+J41 -> -406960.26 | L41: =MIN(J41:J51) -> -15478.265
A42: 27 | B42: =IF(Inputs!B22=0,1,1/(1+EXP(-Inputs!B22*(A42-Inputs!B21)))) -> 1 | C42: =IF(A42-Inputs!B23<1,0,$B$9*IF(Inputs!B22=0,1,1/(1+EXP(-Inputs!B22*(A42-Inputs!B23-Inputs!B21))))) -> 1.2 | D42: =D41*(1-$B$5)+IF(A42-Inputs!B17<1,0,OFFSET(C42,-Inputs!B17,0)*(1-$B$5)^Inputs!B17) -> 14.185782 | E42: =IF(D42>0,F42/D42,0) -> 101.98063 | F42: =F41*(1-$B$5)*(1+$B$6)+IF(A42-Inputs!B17<1,0,OFFSET(C42,-Inputs!B17,0)*(1-$B$5)^Inputs!B17)*$B$3 -> 1446.6749 | G42: =F42*$B$4 -> 1012.6725 | H42: =$B$9*B42*$B$7 -> 120 | I42: =$B$8 -> 16364 | J42: =G42-H42-I42 -> -15471.328 | K42: =K41+J42 -> -422431.58 | L42: =MIN(J42:J51) -> -15471.328
A43: 28 | B43: =IF(Inputs!B22=0,1,1/(1+EXP(-Inputs!B22*(A43-Inputs!B21)))) -> 1 | C43: =IF(A43-Inputs!B23<1,0,$B$9*IF(Inputs!B22=0,1,1/(1+EXP(-Inputs!B22*(A43-Inputs!B23-Inputs!B21))))) -> 1.2 | D43: =D42*(1-$B$5)+IF(A43-Inputs!B17<1,0,OFFSET(C43,-Inputs!B17,0)*(1-$B$5)^Inputs!B17) -> 14.308777 | E43: =IF(D43>0,F43/D43,0) -> 101.74816 | F43: =F42*(1-$B$5)*(1+$B$6)+IF(A43-Inputs!B17<1,0,OFFSET(C43,-Inputs!B17,0)*(1-$B$5)^Inputs!B17)*$B$3 -> 1455.8917 | G43: =F43*$B$4 -> 1019.1242 | H43: =$B$9*B43*$B$7 -> 120 | I43: =$B$8 -> 16364 | J43: =G43-H43-I43 -> -15464.876 | K43: =K42+J43 -> -437896.46 | L43: =MIN(J43:J51) -> -15464.876
A44: 29 | B44: =IF(Inputs!B22=0,1,1/(1+EXP(-Inputs!B22*(A44-Inputs!B21)))) -> 1 | C44: =IF(A44-Inputs!B23<1,0,$B$9*IF(Inputs!B22=0,1,1/(1+EXP(-Inputs!B22*(A44-Inputs!B23-Inputs!B21))))) -> 1.2 | D44: =D43*(1-$B$5)+IF(A44-Inputs!B17<1,0,OFFSET(C44,-Inputs!B17,0)*(1-$B$5)^Inputs!B17) -> 14.423163 | E44: =IF(D44>0,F44/D44,0) -> 101.53552 | F44: =F43*(1-$B$5)*(1+$B$6)+IF(A44-Inputs!B17<1,0,OFFSET(C44,-Inputs!B17,0)*(1-$B$5)^Inputs!B17)*$B$3 -> 1464.4633 | G44: =F44*$B$4 -> 1025.1243 | H44: =$B$9*B44*$B$7 -> 120 | I44: =$B$8 -> 16364 | J44: =G44-H44-I44 -> -15458.876 | K44: =K43+J44 -> -453355.34 | L44: =MIN(J44:J51) -> -15458.876
A45: 30 | B45: =IF(Inputs!B22=0,1,1/(1+EXP(-Inputs!B22*(A45-Inputs!B21)))) -> 1 | C45: =IF(A45-Inputs!B23<1,0,$B$9*IF(Inputs!B22=0,1,1/(1+EXP(-Inputs!B22*(A45-Inputs!B23-Inputs!B21))))) -> 1.2 | D45: =D44*(1-$B$5)+IF(A45-Inputs!B17<1,0,OFFSET(C45,-Inputs!B17,0)*(1-$B$5)^Inputs!B17) -> 14.529542 | E45: =IF(D45>0,F45/D45,0) -> 101.34076 | F45: =F44*(1-$B$5)*(1+$B$6)+IF(A45-Inputs!B17<1,0,OFFSET(C45,-Inputs!B17,0)*(1-$B$5)^Inputs!B17)*$B$3 -> 1472.4349 | G45: =F45*$B$4 -> 1030.7044 | H45: =$B$9*B45*$B$7 -> 120 | I45: =$B$8 -> 16364 | J45: =G45-H45-I45 -> -15453.296 | K45: =K44+J45 -> -468808.63 | L45: =MIN(J45:J51) -> -15453.296
A46: 31 | B46: =IF(Inputs!B22=0,1,1/(1+EXP(-Inputs!B22*(A46-Inputs!B21)))) -> 1 | C46: =IF(A46-Inputs!B23<1,0,$B$9*IF(Inputs!B22=0,1,1/(1+EXP(-Inputs!B22*(A46-Inputs!B23-Inputs!B21))))) -> 1.2 | D46: =D45*(1-$B$5)+IF(A46-Inputs!B17<1,0,OFFSET(C46,-Inputs!B17,0)*(1-$B$5)^Inputs!B17) -> 14.628474 | E46: =IF(D46>0,F46/D46,0) -> 101.16219 | F46: =F45*(1-$B$5)*(1+$B$6)+IF(A46-Inputs!B17<1,0,OFFSET(C46,-Inputs!B17,0)*(1-$B$5)^Inputs!B17)*$B$3 -> 1479.8484 | G46: =F46*$B$4 -> 1035.8939 | H46: =$B$9*B46*$B$7 -> 120 | I46: =$B$8 -> 16364 | J46: =G46-H46-I46 -> -15448.106 | K46: =K45+J46 -> -484256.74 | L46: =MIN(J46:J51) -> -15448.106
A47: 32 | B47: =IF(Inputs!B22=0,1,1/(1+EXP(-Inputs!B22*(A47-Inputs!B21)))) -> 1 | C47: =IF(A47-Inputs!B23<1,0,$B$9*IF(Inputs!B22=0,1,1/(1+EXP(-Inputs!B22*(A47-Inputs!B23-Inputs!B21))))) -> 1.2 | D47: =D46*(1-$B$5)+IF(A47-Inputs!B17<1,0,OFFSET(C47,-Inputs!B17,0)*(1-$B$5)^Inputs!B17) -> 14.72048 | E47: =IF(D47>0,F47/D47,0) -> 100.99827 | F47: =F46*(1-$B$5)*(1+$B$6)+IF(A47-Inputs!B17<1,0,OFFSET(C47,-Inputs!B17,0)*(1-$B$5)^Inputs!B17)*$B$3 -> 1486.743 | G47: =F47*$B$4 -> 1040.7201 | H47: =$B$9*B47*$B$7 -> 120 | I47: =$B$8 -> 16364 | J47: =G47-H47-I47 -> -15443.28 | K47: =K46+J47 -> -499700.02 | L47: =MIN(J47:J51) -> -15443.28
A48: 33 | B48: =IF(Inputs!B22=0,1,1/(1+EXP(-Inputs!B22*(A48-Inputs!B21)))) -> 1 | C48: =IF(A48-Inputs!B23<1,0,$B$9*IF(Inputs!B22=0,1,1/(1+EXP(-Inputs!B22*(A48-Inputs!B23-Inputs!B21))))) -> 1.2 | D48: =D47*(1-$B$5)+IF(A48-Inputs!B17<1,0,OFFSET(C48,-Inputs!B17,0)*(1-$B$5)^Inputs!B17) -> 14.806047 | E48: =IF(D48>0,F48/D48,0) -> 100.84765 | F48: =F47*(1-$B$5)*(1+$B$6)+IF(A48-Inputs!B17<1,0,OFFSET(C48,-Inputs!B17,0)*(1-$B$5)^Inputs!B17)*$B$3 -> 1493.155 | G48: =F48*$B$4 -> 1045.2085 | H48: =$B$9*B48*$B$7 -> 120 | I48: =$B$8 -> 16364 | J48: =G48-H48-I48 -> -15438.791 | K48: =K47+J48 -> -515138.81 | L48: =MIN(J48:J51) -> -15438.791
A49: 34 | B49: =IF(Inputs!B22=0,1,1/(1+EXP(-Inputs!B22*(A49-Inputs!B21)))) -> 1 | C49: =IF(A49-Inputs!B23<1,0,$B$9*IF(Inputs!B22=0,1,1/(1+EXP(-Inputs!B22*(A49-Inputs!B23-Inputs!B21))))) -> 1.2 | D49: =D48*(1-$B$5)+IF(A49-Inputs!B17<1,0,OFFSET(C49,-Inputs!B17,0)*(1-$B$5)^Inputs!B17) -> 14.885624 | E49: =IF(D49>0,F49/D49,0) -> 100.70913 | F49: =F48*(1-$B$5)*(1+$B$6)+IF(A49-Inputs!B17<1,0,OFFSET(C49,-Inputs!B17,0)*(1-$B$5)^Inputs!B17)*$B$3 -> 1499.1182 | G49: =F49*$B$4 -> 1049.3827 | H49: =$B$9*B49*$B$7 -> 120 | I49: =$B$8 -> 16364 | J49: =G49-H49-I49 -> -15434.617 | K49: =K48+J49 -> -530573.43 | L49: =MIN(J49:J51) -> -15434.617
A50: 35 | B50: =IF(Inputs!B22=0,1,1/(1+EXP(-Inputs!B22*(A50-Inputs!B21)))) -> 1 | C50: =IF(A50-Inputs!B23<1,0,$B$9*IF(Inputs!B22=0,1,1/(1+EXP(-Inputs!B22*(A50-Inputs!B23-Inputs!B21))))) -> 1.2 | D50: =D49*(1-$B$5)+IF(A50-Inputs!B17<1,0,OFFSET(C50,-Inputs!B17,0)*(1-$B$5)^Inputs!B17) -> 14.95963 | E50: =IF(D50>0,F50/D50,0) -> 100.58163 | F50: =F49*(1-$B$5)*(1+$B$6)+IF(A50-Inputs!B17<1,0,OFFSET(C50,-Inputs!B17,0)*(1-$B$5)^Inputs!B17)*$B$3 -> 1504.6639 | G50: =F50*$B$4 -> 1053.2647 | H50: =$B$9*B50*$B$7 -> 120 | I50: =$B$8 -> 16364 | J50: =G50-H50-I50 -> -15430.735 | K50: =K49+J50 -> -546004.16 | L50: =MIN(J50:J51) -> -15430.735
A51: 36 | B51: =IF(Inputs!B22=0,1,1/(1+EXP(-Inputs!B22*(A51-Inputs!B21)))) -> 1 | C51: =IF(A51-Inputs!B23<1,0,$B$9*IF(Inputs!B22=0,1,1/(1+EXP(-Inputs!B22*(A51-Inputs!B23-Inputs!B21))))) -> 1.2 | D51: =D50*(1-$B$5)+IF(A51-Inputs!B17<1,0,OFFSET(C51,-Inputs!B17,0)*(1-$B$5)^Inputs!B17) -> 15.028456 | E51: =IF(D51>0,F51/D51,0) -> 100.46418 | F51: =F50*(1-$B$5)*(1+$B$6)+IF(A51-Inputs!B17<1,0,OFFSET(C51,-Inputs!B17,0)*(1-$B$5)^Inputs!B17)*$B$3 -> 1509.8214 | G51: =F51*$B$4 -> 1056.875 | H51: =$B$9*B51*$B$7 -> 120 | I51: =$B$8 -> 16364 | J51: =G51-H51-I51 -> -15427.125 | K51: =K50+J51 -> -561431.29 | L51: =MIN(J51) -> -15427.125
A53: Break-even month (net ≥ 0 from then on) | B53: =IFERROR(INDEX(A16:A51,MATCH(TRUE(),INDEX(L16:L51>=0,0),0)),"none") -> none
A54: Peak capital need | B54: =MAX(0,Inputs!B16,-MIN(K16:K51)) -> 561431.29
A55: Reference customers, 3y (segment × comparable penetration) | B55: =Inputs!B24*Inputs!D25 -> 37.68
A56: Bottom-up customers, month 36 (same 3-year window as the reference) | B56: =D51 -> 15.028456
A57: Ratio to reference | B57: =IF(B55>0,B56/B55,0) -> 0.39884437
A58: Position | B58: =IF(B57>1,"above_comparables",IF(B57<0.1,"far_below_comparables","within_range")) -> within_range

Sheet Optimistic
A1: Optimistic case
A3: Revenue per customer-month (ARPU₀) | B3: =Inputs!E5 -> 169
A4: Gross margin | B4: =Inputs!E6 -> 0.9
A5: Monthly churn | B5: =Inputs!D7 -> 0.03
A6: Monthly expansion | B6: =Inputs!E8 -> 0
A7: Blended CAC | B7: =Inputs!D11 -> 100
A8: Fixed burn / month | B8: =Inputs!B14*Inputs!D10+Inputs!B15 -> 7576
A9: New customers / month at full capacity | B9: =Inputs!E9 -> 2.4
A10: LTV (lifetime contribution, 60-mo cap) | B10: =B3*B4*(1-B5)^Inputs!B17*IF(ABS(1-(1-B5)*(1+B6))<0.000001,MAX(0,60-Inputs!B17),(1-((1-B5)*(1+B6))^MAX(0,60-Inputs!B17))/(1-(1-B5)*(1+B6))) -> 4102.6102
A11: LTV / CAC (cash) | B11: =IF(B7>0,B10/B7,"n/a") -> 41.026102
A12: Payback (months, cumulative; "none" = not within 60) | B12: =IF(B3*B4<=0,"none",IF(B7<=0,1+Inputs!B17,IF((1-B5)*(1+B6)<=0,IF(B7<=B3*B4*(1-B5)^Inputs!B17,1+Inputs!B17,"none"),IF(ABS(1-(1-B5)*(1+B6))<0.000001,IF(B7/(B3*B4*(1-B5)^Inputs!B17)<=60-Inputs!B17,ROUNDUP(B7/(B3*B4*(1-B5)^Inputs!B17),0)+Inputs!B17,"none"),IF(1-B7*(1-(1-B5)*(1+B6))/(B3*B4*(1-B5)^Inputs!B17)<=0,"none",IF(ROUNDUP(LN(1-B7*(1-(1-B5)*(1+B6))/(B3*B4*(1-B5)^Inputs!B17))/LN((1-B5)*(1+B6)),0)<=60-Inputs!B17,ROUNDUP(LN(1-B7*(1-(1-B5)*(1+B6))/(B3*B4*(1-B5)^Inputs!B17))/LN((1-B5)*(1+B6)),0)+Inputs!B17,"none")))))) -> 2
A15: Month | B15: Ramp | C15: New customers (arrivals) | D15: Paying customers | E15: ARPU (derived) | F15: Revenue | G15: Gross profit | H15: Acquisition spend | I15: Fixed burn | J15: Net cash flow | K15: Cumulative cash | L15: Lowest net from here on
A16: 1 | B16: =IF(Inputs!B22=0,1,1/(1+EXP(-Inputs!B22*(A16-Inputs!B21)))) -> 0.5 | C16: =IF(A16-Inputs!B23<1,0,$B$9*IF(Inputs!B22=0,1,1/(1+EXP(-Inputs!B22*(A16-Inputs!B23-Inputs!B21))))) -> 1.2 | D16: =Inputs!B19*(1-$B$5)+IF(A16-Inputs!B17<1,0,OFFSET(C16,-Inputs!B17,0)*(1-$B$5)^Inputs!B17) -> 5.82 | E16: =IF(D16>0,F16/D16,0) -> 149 | F16: =Inputs!B20*(1-$B$5)*(1+$B$6)+IF(A16-Inputs!B17<1,0,OFFSET(C16,-Inputs!B17,0)*(1-$B$5)^Inputs!B17)*$B$3 -> 867.18 | G16: =F16*$B$4 -> 780.462 | H16: =$B$9*B16*$B$7 -> 120 | I16: =$B$8 -> 7576 | J16: =G16-H16-I16 -> -6915.538 | K16: =J16-Inputs!B16 -> -6915.538 | L16: =MIN(J16:J51) -> -6915.538
A17: 2 | B17: =IF(Inputs!B22=0,1,1/(1+EXP(-Inputs!B22*(A17-Inputs!B21)))) -> 0.73105858 | C17: =IF(A17-Inputs!B23<1,0,$B$9*IF(Inputs!B22=0,1,1/(1+EXP(-Inputs!B22*(A17-Inputs!B23-Inputs!B21))))) -> 1.7545406 | D17: =D16*(1-$B$5)+IF(A17-Inputs!B17<1,0,OFFSET(C17,-Inputs!B17,0)*(1-$B$5)^Inputs!B17) -> 6.8094 | E17: =IF(D17>0,F17/D17,0) -> 152.4188 | F17: =F16*(1-$B$5)*(1+$B$6)+IF(A17-Inputs!B17<1,0,OFFSET(C17,-Inputs!B17,0)*(1-$B$5)^Inputs!B17)*$B$3 -> 1037.8806 | G17: =F17*$B$4 -> 934.09254 | H17: =$B$9*B17*$B$7 -> 175.45406 | I17: =$B$8 -> 7576 | J17: =G17-H17-I17 -> -6817.3615 | K17: =K16+J17 -> -13732.9 | L17: =MIN(J17:J51) -> -6817.3615
A18: 3 | B18: =IF(Inputs!B22=0,1,1/(1+EXP(-Inputs!B22*(A18-Inputs!B21)))) -> 0.88079708 | C18: =IF(A18-Inputs!B23<1,0,$B$9*IF(Inputs!B22=0,1,1/(1+EXP(-Inputs!B22*(A18-Inputs!B23-Inputs!B21))))) -> 2.113913 | D18: =D17*(1-$B$5)+IF(A18-Inputs!B17<1,0,OFFSET(C18,-Inputs!B17,0)*(1-$B$5)^Inputs!B17) -> 8.3070224 | E18: =IF(D18>0,F18/D18,0) -> 155.81588 | F18: =F17*(1-$B$5)*(1+$B$6)+IF(A18-Inputs!B17<1,0,OFFSET(C18,-Inputs!B17,0)*(1-$B$5)^Inputs!B17)*$B$3 -> 1294.366 | G18: =F18*$B$4 -> 1164.9294 | H18: =$B$9*B18*$B$7 -> 211.3913 | I18: =$B$8 -> 7576 | J18: =G18-H18-I18 -> -6622.4619 | K18: =K17+J18 -> -20355.361 | L18: =MIN(J18:J51) -> -6622.4619
A19: 4 | B19: =IF(Inputs!B22=0,1,1/(1+EXP(-Inputs!B22*(A19-Inputs!B21)))) -> 0.95257413 | C19: =IF(A19-Inputs!B23<1,0,$B$9*IF(Inputs!B22=0,1,1/(1+EXP(-Inputs!B22*(A19-Inputs!B23-Inputs!B21))))) -> 2.2861779 | D19: =D18*(1-$B$5)+IF(A19-Inputs!B17<1,0,OFFSET(C19,-Inputs!B17,0)*(1-$B$5)^Inputs!B17) -> 10.108307 | E19: =IF(D19>0,F19/D19,0) -> 158.49031 | F19: =F18*(1-$B$5)*(1+$B$6)+IF(A19-Inputs!B17<1,0,OFFSET(C19,-Inputs!B17,0)*(1-$B$5)^Inputs!B17)*$B$3 -> 1602.0688 | G19: =F19*$B$4 -> 1441.8619 | H19: =$B$9*B19*$B$7 -> 228.61779 | I19: =$B$8 -> 7576 | J19: =G19-H19-I19 -> -6362.7559 | K19: =K18+J19 -> -26718.117 | L19: =MIN(J19:J51) -> -6362.7559
A20: 5 | B20: =IF(Inputs!B22=0,1,1/(1+EXP(-Inputs!B22*(A20-Inputs!B21)))) -> 0.98201379 | C20: =IF(A20-Inputs!B23<1,0,$B$9*IF(Inputs!B22=0,1,1/(1+EXP(-Inputs!B22*(A20-Inputs!B23-Inputs!B21))))) -> 2.3568331 | D20: =D19*(1-$B$5)+IF(A20-Inputs!B17<1,0,OFFSET(C20,-Inputs!B17,0)*(1-$B$5)^Inputs!B17) -> 12.022651 | E20: =IF(D20>0,F20/D20,0) -> 160.42884 | F20: =F19*(1-$B$5)*(1+$B$6)+IF(A20-Inputs!B17<1,0,OFFSET(C20,-Inputs!B17,0)*(1-$B$5)^Inputs!B17)*$B$3 -> 1928.7799 | G20: =F20*$B$4 -> 1735.9019 | H20: =$B$9*B20*$B$7 -> 235.68331 | I20: =$B$8 -> 7576 | J20: =G20-H20-I20 -> -6075.7814 | K20: =K19+J20 -> -32793.899 | L20: =MIN(J20:J51) -> -6075.7814
A21: 6 | B21: =IF(Inputs!B22=0,1,1/(1+EXP(-Inputs!B22*(A21-Inputs!B21)))) -> 0.99330715 | C21: =IF(A21-Inputs!B23<1,0,$B$9*IF(Inputs!B22=0,1,1/(1+EXP(-Inputs!B22*(A21-Inputs!B23-Inputs!B21))))) -> 2.3839372 | D21: =D20*(1-$B$5)+IF(A21-Inputs!B17<1,0,OFFSET(C21,-Inputs!B17,0)*(1-$B$5)^Inputs!B17) -> 13.948099 | E21: =IF(D21>0,F21/D21,0) -> 161.83367 | F21: =F20*(1-$B$5)*(1+$B$6)+IF(A21-Inputs!B17<1,0,OFFSET(C21,-Inputs!B17,0)*(1-$B$5)^Inputs!B17)*$B$3 -> 2257.2721 | G21: =F21*$B$4 -> 2031.5449 | H21: =$B$9*B21*$B$7 -> 238.39372 | I21: =$B$8 -> 7576 | J21: =G21-H21-I21 -> -5782.8488 | K21: =K20+J21 -> -38576.747 | L21: =MIN(J21:J51) -> -5782.8488
A22: 7 | B22: =IF(Inputs!B22=0,1,1/(1+EXP(-Inputs!B22*(A22-Inputs!B21)))) -> 0.99752738 | C22: =IF(A22-Inputs!B23<1,0,$B$9*IF(Inputs!B22=0,1,1/(1+EXP(-Inputs!B22*(A22-Inputs!B23-Inputs!B21))))) -> 2.3940657 | D22: =D21*(1-$B$5)+IF(A22-Inputs!B17<1,0,OFFSET(C22,-Inputs!B17,0)*(1-$B$5)^Inputs!B17) -> 15.842075 | E22: =IF(D22>0,F22/D22,0) -> 162.87972 | F22: =F21*(1-$B$5)*(1+$B$6)+IF(A22-Inputs!B17<1,0,OFFSET(C22,-Inputs!B17,0)*(1-$B$5)^Inputs!B17)*$B$3 -> 2580.3528 | G22: =F22*$B$4 -> 2322.3175 | H22: =$B$9*B22*$B$7 -> 239.40657 | I22: =$B$8 -> 7576 | J22: =G22-H22-I22 -> -5493.0891 | K22: =K21+J22 -> -44069.837 | L22: =MIN(J22:J51) -> -5493.0891
A23: 8 | B23: =IF(Inputs!B22=0,1,1/(1+EXP(-Inputs!B22*(A23-Inputs!B21)))) -> 0.99908895 | C23: =IF(A23-Inputs!B23<1,0,$B$9*IF(Inputs!B22=0,1,1/(1+EXP(-Inputs!B22*(A23-Inputs!B23-Inputs!B21))))) -> 2.3978135 | D23: =D22*(1-$B$5)+IF(A23-Inputs!B17<1,0,OFFSET(C23,-Inputs!B17,0)*(1-$B$5)^Inputs!B17) -> 17.689057 | E23: =IF(D23>0,F23/D23,0) -> 163.6832 | F23: =F22*(1-$B$5)*(1+$B$6)+IF(A23-Inputs!B17<1,0,OFFSET(C23,-Inputs!B17,0)*(1-$B$5)^Inputs!B17)*$B$3 -> 2895.4014 | G23: =F23*$B$4 -> 2605.8613 | H23: =$B$9*B23*$B$7 -> 239.78135 | I23: =$B$8 -> 7576 | J23: =G23-H23-I23 -> -5209.9201 | K23: =K22+J23 -> -49279.757 | L23: =MIN(J23:J51) -> -5209.9201
A24: 9 | B24: =IF(Inputs!B22=0,1,1/(1+EXP(-Inputs!B22*(A24-Inputs!B21)))) -> 0.99966465 | C24: =IF(A24-Inputs!B23<1,0,$B$9*IF(Inputs!B22=0,1,1/(1+EXP(-Inputs!B22*(A24-Inputs!B23-Inputs!B21))))) -> 2.3991952 | D24: =D23*(1-$B$5)+IF(A24-Inputs!B17<1,0,OFFSET(C24,-Inputs!B17,0)*(1-$B$5)^Inputs!B17) -> 19.484264 | E24: =IF(D24>0,F24/D24,0) -> 164.31788 | F24: =F23*(1-$B$5)*(1+$B$6)+IF(A24-Inputs!B17<1,0,OFFSET(C24,-Inputs!B17,0)*(1-$B$5)^Inputs!B17)*$B$3 -> 3201.6129 | G24: =F24*$B$4 -> 2881.4516 | H24: =$B$9*B24*$B$7 -> 239.91952 | I24: =$B$8 -> 7576 | J24: =G24-H24-I24 -> -4934.4679 | K24: =K23+J24 -> -54214.225 | L24: =MIN(J24:J51) -> -4934.4679
A25: 10 | B25: =IF(Inputs!B22=0,1,1/(1+EXP(-Inputs!B22*(A25-Inputs!B21)))) -> 0.99987661 | C25: =IF(A25-Inputs!B23<1,0,$B$9*IF(Inputs!B22=0,1,1/(1+EXP(-Inputs!B22*(A25-Inputs!B23-Inputs!B21))))) -> 2.3997039 | D25: =D24*(1-$B$5)+IF(A25-Inputs!B17<1,0,OFFSET(C25,-Inputs!B17,0)*(1-$B$5)^Inputs!B17) -> 21.226956 | E25: =IF(D25>0,F25/D25,0) -> 164.8312 | F25: =F24*(1-$B$5)*(1+$B$6)+IF(A25-Inputs!B17<1,0,OFFSET(C25,-Inputs!B17,0)*(1-$B$5)^Inputs!B17)*$B$3 -> 3498.8646 | G25: =F25*$B$4 -> 3148.9781 | H25: =$B$9*B25*$B$7 -> 239.97039 | I25: =$B$8 -> 7576 | J25: =G25-H25-I25 -> -4666.9923 | K25: =K24+J25 -> -58881.217 | L25: =MIN(J25:J51) -> -4666.9923
A26: 11 | B26: =IF(Inputs!B22=0,1,1/(1+EXP(-Inputs!B22*(A26-Inputs!B21)))) -> 0.9999546 | C26: =IF(A26-Inputs!B23<1,0,$B$9*IF(Inputs!B22=0,1,1/(1+EXP(-Inputs!B22*(A26-Inputs!B23-Inputs!B21))))) -> 2.399891 | D26: =D25*(1-$B$5)+IF(A26-Inputs!B17<1,0,OFFSET(C26,-Inputs!B17,0)*(1-$B$5)^Inputs!B17) -> 22.91786 | E26: =IF(D26>0,F26/D26,0) -> 165.25462 | F26: =F25*(1-$B$5)*(1+$B$6)+IF(A26-Inputs!B17<1,0,OFFSET(C26,-Inputs!B17,0)*(1-$B$5)^Inputs!B17)*$B$3 -> 3787.2821 | G26: =F26*$B$4 -> 3408.5539 | H26: =$B$9*B26*$B$7 -> 239.9891 | I26: =$B$8 -> 7576 | J26: =G26-H26-I26 -> -4407.4352 | K26: =K25+J26 -> -63288.652 | L26: =MIN(J26:J51) -> -4407.4352
A27: 12 | B27: =IF(Inputs!B22=0,1,1/(1+EXP(-Inputs!B22*(A27-Inputs!B21)))) -> 0.9999833 | C27: =IF(A27-Inputs!B23<1,0,$B$9*IF(Inputs!B22=0,1,1/(1+EXP(-Inputs!B22*(A27-Inputs!B23-Inputs!B21))))) -> 2.3999599 | D27: =D26*(1-$B$5)+IF(A27-Inputs!B17<1,0,OFFSET(C27,-Inputs!B17,0)*(1-$B$5)^Inputs!B17) -> 24.558218 | E27: =IF(D27>0,F27/D27,0) -> 165.60964 | F27: =F26*(1-$B$5)*(1+$B$6)+IF(A27-Inputs!B17<1,0,OFFSET(C27,-Inputs!B17,0)*(1-$B$5)^Inputs!B17)*$B$3 -> 4067.0778 | G27: =F27*$B$4 -> 3660.37 | H27: =$B$9*B27*$B$7 -> 239.99599 | I27: =$B$8 -> 7576 | J27: =G27-H27-I27 -> -4155.626 | K27: =K26+J27 -> -67444.278 | L27: =MIN(J27:J51) -> -4155.626
A28: 13 | B28: =IF(Inputs!B22=0,1,1/(1+EXP(-Inputs!B22*(A28-Inputs!B21)))) -> 0.99999386 | C28: =IF(A28-Inputs!B23<1,0,$B$9*IF(Inputs!B22=0,1,1/(1+EXP(-Inputs!B22*(A28-Inputs!B23-Inputs!B21))))) -> 2.3999853 | D28: =D27*(1-$B$5)+IF(A28-Inputs!B17<1,0,OFFSET(C28,-Inputs!B17,0)*(1-$B$5)^Inputs!B17) -> 26.149433 | E28: =IF(D28>0,F28/D28,0) -> 165.91147 | F28: =F27*(1-$B$5)*(1+$B$6)+IF(A28-Inputs!B17<1,0,OFFSET(C28,-Inputs!B17,0)*(1-$B$5)^Inputs!B17)*$B$3 -> 4338.4909 | G28: =F28*$B$4 -> 3904.6418 | H28: =$B$9*B28*$B$7 -> 239.99853 | I28: =$B$8 -> 7576 | J28: =G28-H28-I28 -> -3911.3567 | K28: =K27+J28 -> -71355.635 | L28: =MIN(J28:J51) -> -3911.3567
A29: 14 | B29: =IF(Inputs!B22=0,1,1/(1+EXP(-Inputs!B22*(A29-Inputs!B21)))) -> 0.99999774 | C29: =IF(A29-Inputs!B23<1,0,$B$9*IF(Inputs!B22=0,1,1/(1+EXP(-Inputs!B22*(A29-Inputs!B23-Inputs!B21))))) -> 2.3999946 | D29: =D28*(1-$B$5)+IF(A29-Inputs!B17<1,0,OFFSET(C29,-Inputs!B17,0)*(1-$B$5)^Inputs!B17) -> 27.692935 | E29: =IF(D29>0,F29/D29,0) -> 166.17111 | F29: =F28*(1-$B$5)*(1+$B$6)+IF(A29-Inputs!B17<1,0,OFFSET(C29,-Inputs!B17,0)*(1-$B$5)^Inputs!B17)*$B$3 -> 4601.7657 | G29: =F29*$B$4 -> 4141.5892 | H29: =$B$9*B29*$B$7 -> 239.99946 | I29: =$B$8 -> 7576 | J29: =G29-H29-I29 -> -3674.4103 | K29: =K28+J29 -> -75030.045 | L29: =MIN(J29:J51) -> -3674.4103
A30: 15 | B30: =IF(Inputs!B22=0,1,1/(1+EXP(-Inputs!B22*(A30-Inputs!B21)))) -> 0.99999917 | C30: =IF(A30-Inputs!B23<1,0,$B$9*IF(Inputs!B22=0,1,1/(1+EXP(-Inputs!B22*(A30-Inputs!B23-Inputs!B21))))) -> 2.399998 | D30: =D29*(1-$B$5)+IF(A30-Inputs!B17<1,0,OFFSET(C30,-Inputs!B17,0)*(1-$B$5)^Inputs!B17) -> 29.190142 | E30: =IF(D30>0,F30/D30,0) -> 166.39672 | F30: =F29*(1-$B$5)*(1+$B$6)+IF(A30-Inputs!B17<1,0,OFFSET(C30,-Inputs!B17,0)*(1-$B$5)^Inputs!B17)*$B$3 -> 4857.1439 | G30: =F30*$B$4 -> 4371.4295 | H30: =$B$9*B30*$B$7 -> 239.9998 | I30: =$B$8 -> 7576 | J30: =G30-H30-I30 -> -3444.5703 | K30: =K29+J30 -> -78474.615 | L30: =MIN(J30:J51) -> -3444.5703
A31: 16 | B31: =IF(Inputs!B22=0,1,1/(1+EXP(-Inputs!B22*(A31-Inputs!B21)))) -> 0.99999969 | C31: =IF(A31-Inputs!B23<1,0,$B$9*IF(Inputs!B22=0,1,1/(1+EXP(-Inputs!B22*(A31-Inputs!B23-Inputs!B21))))) -> 2.3999993 | D31: =D30*(1-$B$5)+IF(A31-Inputs!B17<1,0,OFFSET(C31,-Inputs!B17,0)*(1-$B$5)^Inputs!B17) -> 30.642436 | E31: =IF(D31>0,F31/D31,0) -> 166.5945 | F31: =F30*(1-$B$5)*(1+$B$6)+IF(A31-Inputs!B17<1,0,OFFSET(C31,-Inputs!B17,0)*(1-$B$5)^Inputs!B17)*$B$3 -> 5104.8612 | G31: =F31*$B$4 -> 4594.3751 | H31: =$B$9*B31*$B$7 -> 239.99993 | I31: =$B$8 -> 7576 | J31: =G31-H31-I31 -> -3221.6248 | K31: =K30+J31 -> -81696.24 | L31: =MIN(J31:J51) -> -3221.6248
A32: 17 | B32: =IF(Inputs!B22=0,1,1/(1+EXP(-Inputs!B22*(A32-Inputs!B21)))) -> 0.99999989 | C32: =IF(A32-Inputs!B23<1,0,$B$9*IF(Inputs!B22=0,1,1/(1+EXP(-Inputs!B22*(A32-Inputs!B23-Inputs!B21))))) -> 2.3999997 | D32: =D31*(1-$B$5)+IF(A32-Inputs!B17<1,0,OFFSET(C32,-Inputs!B17,0)*(1-$B$5)^Inputs!B17) -> 32.051162 | E32: =IF(D32>0,F32/D32,0) -> 166.76922 | F32: =F31*(1-$B$5)*(1+$B$6)+IF(A32-Inputs!B17<1,0,OFFSET(C32,-Inputs!B17,0)*(1-$B$5)^Inputs!B17)*$B$3 -> 5345.1473 | G32: =F32*$B$4 -> 4810.6325 | H32: =$B$9*B32*$B$7 -> 239.99997 | I32: =$B$8 -> 7576 | J32: =G32-H32-I32 -> -3005.3674 | K32: =K31+J32 -> -84701.608 | L32: =MIN(J32:J51) -> -3005.3674
A33: 18 | B33: =IF(Inputs!B22=0,1,1/(1+EXP(-Inputs!B22*(A33-Inputs!B21)))) -> 0.99999996 | C33: =IF(A33-Inputs!B23<1,0,$B$9*IF(Inputs!B22=0,1,1/(1+EXP(-Inputs!B22*(A33-Inputs!B23-Inputs!B21))))) -> 2.3999999 | D33: =D32*(1-$B$5)+IF(A33-Inputs!B17<1,0,OFFSET(C33,-Inputs!B17,0)*(1-$B$5)^Inputs!B17) -> 33.417627 | E33: =IF(D33>0,F33/D33,0) -> 166.92462 | F33: =F32*(1-$B$5)*(1+$B$6)+IF(A33-Inputs!B17<1,0,OFFSET(C33,-Inputs!B17,0)*(1-$B$5)^Inputs!B17)*$B$3 -> 5578.2248 | G33: =F33*$B$4 -> 5020.4023 | H33: =$B$9*B33*$B$7 -> 239.99999 | I33: =$B$8 -> 7576 | J33: =G33-H33-I33 -> -2795.5977 | K33: =K32+J33 -> -87497.205 | L33: =MIN(J33:J51) -> -2795.5977
A34: 19 | B34: =IF(Inputs!B22=0,1,1/(1+EXP(-Inputs!B22*(A34-Inputs!B21)))) -> 0.99999998 | C34: =IF(A34-Inputs!B23<1,0,$B$9*IF(Inputs!B22=0,1,1/(1+EXP(-Inputs!B22*(A34-Inputs!B23-Inputs!B21))))) -> 2.4 | D34: =D33*(1-$B$5)+IF(A34-Inputs!B17<1,0,OFFSET(C34,-Inputs!B17,0)*(1-$B$5)^Inputs!B17) -> 34.743098 | E34: =IF(D34>0,F34/D34,0) -> 167.06369 | F34: =F33*(1-$B$5)*(1+$B$6)+IF(A34-Inputs!B17<1,0,OFFSET(C34,-Inputs!B17,0)*(1-$B$5)^Inputs!B17)*$B$3 -> 5804.31 | G34: =F34*$B$4 -> 5223.879 | H34: =$B$9*B34*$B$7 -> 240 | I34: =$B$8 -> 7576 | J34: =G34-H34-I34 -> -2592.121 | K34: =K33+J34 -> -90089.326 | L34: =MIN(J34:J51) -> -2592.121
A35: 20 | B35: =IF(Inputs!B22=0,1,1/(1+EXP(-Inputs!B22*(A35-Inputs!B21)))) -> 0.99999999 | C35: =IF(A35-Inputs!B23<1,0,$B$9*IF(Inputs!B22=0,1,1/(1+EXP(-Inputs!B22*(A35-Inputs!B23-Inputs!B21))))) -> 2.4 | D35: =D34*(1-$B$5)+IF(A35-Inputs!B17<1,0,OFFSET(C35,-Inputs!B17,0)*(1-$B$5)^Inputs!B17) -> 36.028805 | E35: =IF(D35>0,F35/D35,0) -> 167.1888 | F35: =F34*(1-$B$5)*(1+$B$6)+IF(A35-Inputs!B17<1,0,OFFSET(C35,-Inputs!B17,0)*(1-$B$5)^Inputs!B17)*$B$3 -> 6023.6127 | G35: =F35*$B$4 -> 5421.2515 | H35: =$B$9*B35*$B$7 -> 240 | I35: =$B$8 -> 7576 | J35: =G35-H35-I35 -> -2394.7485 | K35: =K34+J35 -> -92484.075 | L35: =MIN(J35:J51) -> -2394.7485
A36: 21 | B36: =IF(Inputs!B22=0,1,1/(1+EXP(-Inputs!B22*(A36-Inputs!B21)))) -> 1 | C36: =IF(A36-Inputs!B23<1,0,$B$9*IF(Inputs!B22=0,1,1/(1+EXP(-Inputs!B22*(A36-Inputs!B23-Inputs!B21))))) -> 2.4 | D36: =D35*(1-$B$5)+IF(A36-Inputs!B17<1,0,OFFSET(C36,-Inputs!B17,0)*(1-$B$5)^Inputs!B17) -> 37.275941 | E36: =IF(D36>0,F36/D36,0) -> 167.30192 | F36: =F35*(1-$B$5)*(1+$B$6)+IF(A36-Inputs!B17<1,0,OFFSET(C36,-Inputs!B17,0)*(1-$B$5)^Inputs!B17)*$B$3 -> 6236.3364 | G36: =F36*$B$4 -> 5612.7027 | H36: =$B$9*B36*$B$7 -> 240 | I36: =$B$8 -> 7576 | J36: =G36-H36-I36 -> -2203.2973 | K36: =K35+J36 -> -94687.372 | L36: =MIN(J36:J51) -> -2203.2973
A37: 22 | B37: =IF(Inputs!B22=0,1,1/(1+EXP(-Inputs!B22*(A37-Inputs!B21)))) -> 1 | C37: =IF(A37-Inputs!B23<1,0,$B$9*IF(Inputs!B22=0,1,1/(1+EXP(-Inputs!B22*(A37-Inputs!B23-Inputs!B21))))) -> 2.4 | D37: =D36*(1-$B$5)+IF(A37-Inputs!B17<1,0,OFFSET(C37,-Inputs!B17,0)*(1-$B$5)^Inputs!B17) -> 38.485663 | E37: =IF(D37>0,F37/D37,0) -> 167.40463 | F37: =F36*(1-$B$5)*(1+$B$6)+IF(A37-Inputs!B17<1,0,OFFSET(C37,-Inputs!B17,0)*(1-$B$5)^Inputs!B17)*$B$3 -> 6442.6783 | G37: =F37*$B$4 -> 5798.4104 | H37: =$B$9*B37*$B$7 -> 240 | I37: =$B$8 -> 7576 | J37: =G37-H37-I37 -> -2017.5896 | K37: =K36+J37 -> -96704.962 | L37: =MIN(J37:J51) -> -2017.5896
A38: 23 | B38: =IF(Inputs!B22=0,1,1/(1+EXP(-Inputs!B22*(A38-Inputs!B21)))) -> 1 | C38: =IF(A38-Inputs!B23<1,0,$B$9*IF(Inputs!B22=0,1,1/(1+EXP(-Inputs!B22*(A38-Inputs!B23-Inputs!B21))))) -> 2.4 | D38: =D37*(1-$B$5)+IF(A38-Inputs!B17<1,0,OFFSET(C38,-Inputs!B17,0)*(1-$B$5)^Inputs!B17) -> 39.659093 | E38: =IF(D38>0,F38/D38,0) -> 167.49828 | F38: =F37*(1-$B$5)*(1+$B$6)+IF(A38-Inputs!B17<1,0,OFFSET(C38,-Inputs!B17,0)*(1-$B$5)^Inputs!B17)*$B$3 -> 6642.8299 | G38: =F38*$B$4 -> 5978.5469 | H38: =$B$9*B38*$B$7 -> 240 | I38: =$B$8 -> 7576 | J38: =G38-H38-I38 -> -1837.4531 | K38: =K37+J38 -> -98542.415 | L38: =MIN(J38:J51) -> -1837.4531
A39: 24 | B39: =IF(Inputs!B22=0,1,1/(1+EXP(-Inputs!B22*(A39-Inputs!B21)))) -> 1 | C39: =IF(A39-Inputs!B23<1,0,$B$9*IF(Inputs!B22=0,1,1/(1+EXP(-Inputs!B22*(A39-Inputs!B23-Inputs!B21))))) -> 2.4 | D39: =D38*(1-$B$5)+IF(A39-Inputs!B17<1,0,OFFSET(C39,-Inputs!B17,0)*(1-$B$5)^Inputs!B17) -> 40.79732 | E39: =IF(D39>0,F39/D39,0) -> 167.58397 | F39: =F38*(1-$B$5)*(1+$B$6)+IF(A39-Inputs!B17<1,0,OFFSET(C39,-Inputs!B17,0)*(1-$B$5)^Inputs!B17)*$B$3 -> 6836.977 | G39: =F39*$B$4 -> 6153.2793 | H39: =$B$9*B39*$B$7 -> 240 | I39: =$B$8 -> 7576 | J39: =G39-H39-I39 -> -1662.7207 | K39: =K38+J39 -> -100205.14 | L39: =MIN(J39:J51) -> -1662.7207
A40: 25 | B40: =IF(Inputs!B22=0,1,1/(1+EXP(-Inputs!B22*(A40-Inputs!B21)))) -> 1 | C40: =IF(A40-Inputs!B23<1,0,$B$9*IF(Inputs!B22=0,1,1/(1+EXP(-Inputs!B22*(A40-Inputs!B23-Inputs!B21))))) -> 2.4 | D40: =D39*(1-$B$5)+IF(A40-Inputs!B17<1,0,OFFSET(C40,-Inputs!B17,0)*(1-$B$5)^Inputs!B17) -> 41.9014 | E40: =IF(D40>0,F40/D40,0) -> 167.66265 | F40: =F39*(1-$B$5)*(1+$B$6)+IF(A40-Inputs!B17<1,0,OFFSET(C40,-Inputs!B17,0)*(1-$B$5)^Inputs!B17)*$B$3 -> 7025.2997 | G40: =F40*$B$4 -> 6322.7697 | H40: =$B$9*B40*$B$7 -> 240 | I40: =$B$8 -> 7576 | J40: =G40-H40-I40 -> -1493.2303 | K40: =K39+J40 -> -101698.37 | L40: =MIN(J40:J51) -> -1493.2303
A41: 26 | B41: =IF(Inputs!B22=0,1,1/(1+EXP(-Inputs!B22*(A41-Inputs!B21)))) -> 1 | C41: =IF(A41-Inputs!B23<1,0,$B$9*IF(Inputs!B22=0,1,1/(1+EXP(-Inputs!B22*(A41-Inputs!B23-Inputs!B21))))) -> 2.4 | D41: =D40*(1-$B$5)+IF(A41-Inputs!B17<1,0,OFFSET(C41,-Inputs!B17,0)*(1-$B$5)^Inputs!B17) -> 42.972358 | E41: =IF(D41>0,F41/D41,0) -> 167.7351 | F41: =F40*(1-$B$5)*(1+$B$6)+IF(A41-Inputs!B17<1,0,OFFSET(C41,-Inputs!B17,0)*(1-$B$5)^Inputs!B17)*$B$3 -> 7207.9727 | G41: =F41*$B$4 -> 6487.1754 | H41: =$B$9*B41*$B$7 -> 240 | I41: =$B$8 -> 7576 | J41: =G41-H41-I41 -> -1328.8246 | K41: =K40+J41 -> -103027.19 | L41: =MIN(J41:J51) -> -1328.8246
A42: 27 | B42: =IF(Inputs!B22=0,1,1/(1+EXP(-Inputs!B22*(A42-Inputs!B21)))) -> 1 | C42: =IF(A42-Inputs!B23<1,0,$B$9*IF(Inputs!B22=0,1,1/(1+EXP(-Inputs!B22*(A42-Inputs!B23-Inputs!B21))))) -> 2.4 | D42: =D41*(1-$B$5)+IF(A42-Inputs!B17<1,0,OFFSET(C42,-Inputs!B17,0)*(1-$B$5)^Inputs!B17) -> 44.011188 | E42: =IF(D42>0,F42/D42,0) -> 167.80201 | F42: =F41*(1-$B$5)*(1+$B$6)+IF(A42-Inputs!B17<1,0,OFFSET(C42,-Inputs!B17,0)*(1-$B$5)^Inputs!B17)*$B$3 -> 7385.1655 | G42: =F42*$B$4 -> 6646.649 | H42: =$B$9*B42*$B$7 -> 240 | I42: =$B$8 -> 7576 | J42: =G42-H42-I42 -> -1169.351 | K42: =K41+J42 -> -104196.54 | L42: =MIN(J42:J51) -> -1169.351
A43: 28 | B43: =IF(Inputs!B22=0,1,1/(1+EXP(-Inputs!B22*(A43-Inputs!B21)))) -> 1 | C43: =IF(A43-Inputs!B23<1,0,$B$9*IF(Inputs!B22=0,1,1/(1+EXP(-Inputs!B22*(A43-Inputs!B23-Inputs!B21))))) -> 2.4 | D43: =D42*(1-$B$5)+IF(A43-Inputs!B17<1,0,OFFSET(C43,-Inputs!B17,0)*(1-$B$5)^Inputs!B17) -> 45.018852 | E43: =IF(D43>0,F43/D43,0) -> 167.86396 | F43: =F42*(1-$B$5)*(1+$B$6)+IF(A43-Inputs!B17<1,0,OFFSET(C43,-Inputs!B17,0)*(1-$B$5)^Inputs!B17)*$B$3 -> 7557.0426 | G43: =F43*$B$4 -> 6801.3383 | H43: =$B$9*B43*$B$7 -> 240 | I43: =$B$8 -> 7576 | J43: =G43-H43-I43 -> -1014.6617 | K43: =K42+J43 -> -105211.2 | L43: =MIN(J43:J51) -> -1014.6617
A44: 29 | B44: =IF(Inputs!B22=0,1,1/(1+EXP(-Inputs!B22*(A44-Inputs!B21)))) -> 1 | C44: =IF(A44-Inputs!B23<1,0,$B$9*IF(Inputs!B22=0,1,1/(1+EXP(-Inputs!B22*(A44-Inputs!B23-Inputs!B21))))) -> 2.4 | D44: =D43*(1-$B$5)+IF(A44-Inputs!B17<1,0,OFFSET(C44,-Inputs!B17,0)*(1-$B$5)^Inputs!B17) -> 45.996286 | E44: =IF(D44>0,F44/D44,0) -> 167.92145 | F44: =F43*(1-$B$5)*(1+$B$6)+IF(A44-Inputs!B17<1,0,OFFSET(C44,-Inputs!B17,0)*(1-$B$5)^Inputs!B17)*$B$3 -> 7723.7633 | G44: =F44*$B$4 -> 6951.387 | H44: =$B$9*B44*$B$7 -> 240 | I44: =$B$8 -> 7576 | J44: =G44-H44-I44 -> -864.61304 | K44: =K43+J44 -> -106075.82 | L44: =MIN(J44:J51) -> -864.61304
A45: 30 | B45: =IF(Inputs!B22=0,1,1/(1+EXP(-Inputs!B22*(A45-Inputs!B21)))) -> 1 | C45: =IF(A45-Inputs!B23<1,0,$B$9*IF(Inputs!B22=0,1,1/(1+EXP(-Inputs!B22*(A45-Inputs!B23-Inputs!B21))))) -> 2.4 | D45: =D44*(1-$B$5)+IF(A45-Inputs!B17<1,0,OFFSET(C45,-Inputs!B17,0)*(1-$B$5)^Inputs!B17) -> 46.944398 | E45: =IF(D45>0,F45/D45,0) -> 167.97494 | F45: =F44*(1-$B$5)*(1+$B$6)+IF(A45-Inputs!B17<1,0,OFFSET(C45,-Inputs!B17,0)*(1-$B$5)^Inputs!B17)*$B$3 -> 7885.4824 | G45: =F45*$B$4 -> 7096.9342 | H45: =$B$9*B45*$B$7 -> 240 | I45: =$B$8 -> 7576 | J45: =G45-H45-I45 -> -719.06585 | K45: =K44+J45 -> -106794.88 | L45: =MIN(J45:J51) -> -719.06585
A46: 31 | B46: =IF(Inputs!B22=0,1,1/(1+EXP(-Inputs!B22*(A46-Inputs!B21)))) -> 1 | C46: =IF(A46-Inputs!B23<1,0,$B$9*IF(Inputs!B22=0,1,1/(1+EXP(-Inputs!B22*(A46-Inputs!B23-Inputs!B21))))) -> 2.4 | D46: =D45*(1-$B$5)+IF(A46-Inputs!B17<1,0,OFFSET(C46,-Inputs!B17,0)*(1-$B$5)^Inputs!B17) -> 47.864066 | E46: =IF(D46>0,F46/D46,0) -> 168.0248 | F46: =F45*(1-$B$5)*(1+$B$6)+IF(A46-Inputs!B17<1,0,OFFSET(C46,-Inputs!B17,0)*(1-$B$5)^Inputs!B17)*$B$3 -> 8042.3499 | G46: =F46*$B$4 -> 7238.1149 | H46: =$B$9*B46*$B$7 -> 240 | I46: =$B$8 -> 7576 | J46: =G46-H46-I46 -> -577.88507 | K46: =K45+J46 -> -107372.77 | L46: =MIN(J46:J51) -> -577.88507
A47: 32 | B47: =IF(Inputs!B22=0,1,1/(1+EXP(-Inputs!B22*(A47-Inputs!B21)))) -> 1 | C47: =IF(A47-Inputs!B23<1,0,$B$9*IF(Inputs!B22=0,1,1/(1+EXP(-Inputs!B22*(A47-Inputs!B23-Inputs!B21))))) -> 2.4 | D47: =D46*(1-$B$5)+IF(A47-Inputs!B17<1,0,OFFSET(C47,-Inputs!B17,0)*(1-$B$5)^Inputs!B17) -> 48.756144 | E47: =IF(D47>0,F47/D47,0) -> 168.07136 | F47: =F46*(1-$B$5)*(1+$B$6)+IF(A47-Inputs!B17<1,0,OFFSET(C47,-Inputs!B17,0)*(1-$B$5)^Inputs!B17)*$B$3 -> 8194.5114 | G47: =F47*$B$4 -> 7375.0603 | H47: =$B$9*B47*$B$7 -> 240 | I47: =$B$8 -> 7576 | J47: =G47-H47-I47 -> -440.93972 | K47: =K46+J47 -> -107813.71 | L47: =MIN(J47:J51) -> -440.93972
A48: 33 | B48: =IF(Inputs!B22=0,1,1/(1+EXP(-Inputs!B22*(A48-Inputs!B21)))) -> 1 | C48: =IF(A48-Inputs!B23<1,0,$B$9*IF(Inputs!B22=0,1,1/(1+EXP(-Inputs!B22*(A48-Inputs!B23-Inputs!B21))))) -> 2.4 | D48: =D47*(1-$B$5)+IF(A48-Inputs!B17<1,0,OFFSET(C48,-Inputs!B17,0)*(1-$B$5)^Inputs!B17) -> 49.62146 | E48: =IF(D48>0,F48/D48,0) -> 168.11493 | F48: =F47*(1-$B$5)*(1+$B$6)+IF(A48-Inputs!B17<1,0,OFFSET(C48,-Inputs!B17,0)*(1-$B$5)^Inputs!B17)*$B$3 -> 8342.1081 | G48: =F48*$B$4 -> 7507.8973 | H48: =$B$9*B48*$B$7 -> 240 | I48: =$B$8 -> 7576 | J48: =G48-H48-I48 -> -308.10273 | K48: =K47+J48 -> -108121.81 | L48: =MIN(J48:J51) -> -308.10273
A49: 34 | B49: =IF(Inputs!B22=0,1,1/(1+EXP(-Inputs!B22*(A49-Inputs!B21)))) -> 1 | C49: =IF(A49-Inputs!B23<1,0,$B$9*IF(Inputs!B22=0,1,1/(1+EXP(-Inputs!B22*(A49-Inputs!B23-Inputs!B21))))) -> 2.4 | D49: =D48*(1-$B$5)+IF(A49-Inputs!B17<1,0,OFFSET(C49,-Inputs!B17,0)*(1-$B$5)^Inputs!B17) -> 50.460816 | E49: =IF(D49>0,F49/D49,0) -> 168.15576 | F49: =F48*(1-$B$5)*(1+$B$6)+IF(A49-Inputs!B17<1,0,OFFSET(C49,-Inputs!B17,0)*(1-$B$5)^Inputs!B17)*$B$3 -> 8485.2768 | G49: =F49*$B$4 -> 7636.7492 | H49: =$B$9*B49*$B$7 -> 240 | I49: =$B$8 -> 7576 | J49: =G49-H49-I49 -> -179.25085 | K49: =K48+J49 -> -108301.06 | L49: =MIN(J49:J51) -> -179.25085
A50: 35 | B50: =IF(Inputs!B22=0,1,1/(1+EXP(-Inputs!B22*(A50-Inputs!B21)))) -> 1 | C50: =IF(A50-Inputs!B23<1,0,$B$9*IF(Inputs!B22=0,1,1/(1+EXP(-Inputs!B22*(A50-Inputs!B23-Inputs!B21))))) -> 2.4 | D50: =D49*(1-$B$5)+IF(A50-Inputs!B17<1,0,OFFSET(C50,-Inputs!B17,0)*(1-$B$5)^Inputs!B17) -> 51.274991 | E50: =IF(D50>0,F50/D50,0) -> 168.19409 | F50: =F49*(1-$B$5)*(1+$B$6)+IF(A50-Inputs!B17<1,0,OFFSET(C50,-Inputs!B17,0)*(1-$B$5)^Inputs!B17)*$B$3 -> 8624.1505 | G50: =F50*$B$4 -> 7761.7355 | H50: =$B$9*B50*$B$7 -> 240 | I50: =$B$8 -> 7576 | J50: =G50-H50-I50 -> -54.26452 | K50: =K49+J50 -> -108355.32 | L50: =MIN(J50:J51) -> -54.26452
A51: 36 | B51: =IF(Inputs!B22=0,1,1/(1+EXP(-Inputs!B22*(A51-Inputs!B21)))) -> 1 | C51: =IF(A51-Inputs!B23<1,0,$B$9*IF(Inputs!B22=0,1,1/(1+EXP(-Inputs!B22*(A51-Inputs!B23-Inputs!B21))))) -> 2.4 | D51: =D50*(1-$B$5)+IF(A51-Inputs!B17<1,0,OFFSET(C51,-Inputs!B17,0)*(1-$B$5)^Inputs!B17) -> 52.064742 | E51: =IF(D51>0,F51/D51,0) -> 168.23013 | F51: =F50*(1-$B$5)*(1+$B$6)+IF(A51-Inputs!B17<1,0,OFFSET(C51,-Inputs!B17,0)*(1-$B$5)^Inputs!B17)*$B$3 -> 8758.858 | G51: =F51*$B$4 -> 7882.9722 | H51: =$B$9*B51*$B$7 -> 240 | I51: =$B$8 -> 7576 | J51: =G51-H51-I51 -> 66.972215 | K51: =K50+J51 -> -108288.35 | L51: =MIN(J51) -> 66.972215
A53: Break-even month (net ≥ 0 from then on) | B53: =IFERROR(INDEX(A16:A51,MATCH(TRUE(),INDEX(L16:L51>=0,0),0)),"none") -> 36
A54: Peak capital need | B54: =MAX(0,Inputs!B16,-MIN(K16:K51)) -> 108355.32
A55: Reference customers, 3y (segment × comparable penetration) | B55: =Inputs!B24*Inputs!E25 -> 113.04
A56: Bottom-up customers, month 36 (same 3-year window as the reference) | B56: =D51 -> 52.064742
A57: Ratio to reference | B57: =IF(B55>0,B56/B55,0) -> 0.46058689
A58: Position | B58: =IF(B57>1,"above_comparables",IF(B57<0.1,"far_below_comparables","within_range")) -> within_range
